{
"meta":{"test_sets":[],"test_metrics":[],"learn_metrics":[{"best_value":"Min","name":"Logloss"}],"launch_mode":"Train","parameters":"","iteration_count":1000,"learn_sets":["learn"],"name":"experiment"},
"iterations":[
{"learn":[0.6895264951],"iteration":0,"passed_time":0.001169836034,"remaining_time":1.168666198},
{"learn":[0.6833839645],"iteration":1,"passed_time":0.00258688036,"remaining_time":1.2908533},
{"learn":[0.6768384008],"iteration":2,"passed_time":0.004053244709,"remaining_time":1.347028325},
{"learn":[0.6712704047],"iteration":3,"passed_time":0.005400152861,"remaining_time":1.344638062},
{"learn":[0.6661527714],"iteration":4,"passed_time":0.006651648653,"remaining_time":1.323678082},
{"learn":[0.6610607216],"iteration":5,"passed_time":0.007906739635,"remaining_time":1.3098832},
{"learn":[0.6557717238],"iteration":6,"passed_time":0.009161344601,"remaining_time":1.29960217},
{"learn":[0.6506154409],"iteration":7,"passed_time":0.01048557376,"remaining_time":1.300211146},
{"learn":[0.6452277178],"iteration":8,"passed_time":0.01190576388,"remaining_time":1.310956889},
{"learn":[0.6407023904],"iteration":9,"passed_time":0.01320633402,"remaining_time":1.307427068},
{"learn":[0.6377918906],"iteration":10,"passed_time":0.01387085505,"remaining_time":1.247115967},
{"learn":[0.6326096586],"iteration":11,"passed_time":0.01510566316,"remaining_time":1.2436996},
{"learn":[0.6273595387],"iteration":12,"passed_time":0.01644971514,"remaining_time":1.248912988},
{"learn":[0.6246314134],"iteration":13,"passed_time":0.01719609565,"remaining_time":1.211096451},
{"learn":[0.6198021438],"iteration":14,"passed_time":0.0185141028,"remaining_time":1.215759417},
{"learn":[0.6156783418],"iteration":15,"passed_time":0.01978487248,"remaining_time":1.216769657},
{"learn":[0.6112837649],"iteration":16,"passed_time":0.02103462061,"remaining_time":1.216296003},
{"learn":[0.6072419675],"iteration":17,"passed_time":0.02228572692,"remaining_time":1.215810213},
{"learn":[0.6032711189],"iteration":18,"passed_time":0.02351344452,"remaining_time":1.214036267},
{"learn":[0.599404295],"iteration":19,"passed_time":0.02452719237,"remaining_time":1.201832426},
{"learn":[0.5958333272],"iteration":20,"passed_time":0.02555628168,"remaining_time":1.191409513},
{"learn":[0.5914647451],"iteration":21,"passed_time":0.02682001111,"remaining_time":1.192271403},
{"learn":[0.5880761975],"iteration":22,"passed_time":0.02782190082,"remaining_time":1.181825961},
{"learn":[0.585095023],"iteration":23,"passed_time":0.02897882978,"remaining_time":1.178472411},
{"learn":[0.5816545315],"iteration":24,"passed_time":0.03041395293,"remaining_time":1.186144164},
{"learn":[0.5787292755],"iteration":25,"passed_time":0.03161267964,"remaining_time":1.184259614},
{"learn":[0.574866746],"iteration":26,"passed_time":0.03290977443,"remaining_time":1.18597076},
{"learn":[0.5728533168],"iteration":27,"passed_time":0.03354073036,"remaining_time":1.164342497},
{"learn":[0.569061462],"iteration":28,"passed_time":0.03479178674,"remaining_time":1.164924998},
{"learn":[0.5656450009],"iteration":29,"passed_time":0.03612093832,"remaining_time":1.167910339},
{"learn":[0.5620699214],"iteration":30,"passed_time":0.03751142817,"remaining_time":1.172534642},
{"learn":[0.5587218964],"iteration":31,"passed_time":0.0388215755,"remaining_time":1.174352659},
{"learn":[0.5546843934],"iteration":32,"passed_time":0.04009295469,"remaining_time":1.174845066},
{"learn":[0.551023015],"iteration":33,"passed_time":0.04133899778,"remaining_time":1.174513878},
{"learn":[0.5484988732],"iteration":34,"passed_time":0.04233092082,"remaining_time":1.16712396},
{"learn":[0.5456447944],"iteration":35,"passed_time":0.04388655674,"remaining_time":1.175184464},
{"learn":[0.5434163716],"iteration":36,"passed_time":0.04488938819,"remaining_time":1.16833732},
{"learn":[0.5412482073],"iteration":37,"passed_time":0.04567086276,"remaining_time":1.156193947},
{"learn":[0.5385389499],"iteration":38,"passed_time":0.04668276906,"remaining_time":1.150311309},
{"learn":[0.5360519044],"iteration":39,"passed_time":0.04797127568,"remaining_time":1.151310616},
{"learn":[0.5327483765],"iteration":40,"passed_time":0.04925401933,"remaining_time":1.152063525},
{"learn":[0.5302699654],"iteration":41,"passed_time":0.0506426287,"remaining_time":1.155134245},
{"learn":[0.5274720335],"iteration":42,"passed_time":0.05200688664,"remaining_time":1.157455593},
{"learn":[0.5250245054],"iteration":43,"passed_time":0.05325317939,"remaining_time":1.157046352},
{"learn":[0.5230208528],"iteration":44,"passed_time":0.05450050077,"remaining_time":1.156621739},
{"learn":[0.5201804338],"iteration":45,"passed_time":0.0557634083,"remaining_time":1.156484598},
{"learn":[0.5173847861],"iteration":46,"passed_time":0.05722510689,"remaining_time":1.160330359},
{"learn":[0.514442855],"iteration":47,"passed_time":0.05871932797,"remaining_time":1.164600005},
{"learn":[0.5119017641],"iteration":48,"passed_time":0.05999216521,"remaining_time":1.164337737},
{"learn":[0.5093750183],"iteration":49,"passed_time":0.0612412742,"remaining_time":1.16358421},
{"learn":[0.5080477777],"iteration":50,"passed_time":0.06202043186,"remaining_time":1.154066467},
{"learn":[0.5059628972],"iteration":51,"passed_time":0.0632285427,"remaining_time":1.152704971},
{"learn":[0.5035033997],"iteration":52,"passed_time":0.06460857986,"remaining_time":1.154421229},
{"learn":[0.5022343618],"iteration":53,"passed_time":0.06532753807,"remaining_time":1.144441685},
{"learn":[0.5000279592],"iteration":54,"passed_time":0.06658248923,"remaining_time":1.144008224},
{"learn":[0.4981641941],"iteration":55,"passed_time":0.06760500135,"remaining_time":1.139627166},
{"learn":[0.4961711404],"iteration":56,"passed_time":0.06883936007,"remaining_time":1.138868711},
{"learn":[0.4950291068],"iteration":57,"passed_time":0.0696586141,"remaining_time":1.131351974},
{"learn":[0.4939525399],"iteration":58,"passed_time":0.07049864001,"remaining_time":1.124393564},
{"learn":[0.491716442],"iteration":59,"passed_time":0.07205068074,"remaining_time":1.128793998},
{"learn":[0.4896529877],"iteration":60,"passed_time":0.07306094924,"remaining_time":1.12465953},
{"learn":[0.4874432044],"iteration":61,"passed_time":0.07446015144,"remaining_time":1.126510033},
{"learn":[0.4852574514],"iteration":62,"passed_time":0.0758158971,"remaining_time":1.127611041},
{"learn":[0.4833226004],"iteration":63,"passed_time":0.07726537104,"remaining_time":1.130006051},
{"learn":[0.4824163928],"iteration":64,"passed_time":0.07813531792,"remaining_time":1.123946496},
{"learn":[0.4800744428],"iteration":65,"passed_time":0.07975950115,"remaining_time":1.128717789},
{"learn":[0.4790107133],"iteration":66,"passed_time":0.08067089192,"remaining_time":1.123372271},
{"learn":[0.4767083265],"iteration":67,"passed_time":0.08213115144,"remaining_time":1.125679899},
{"learn":[0.4748221757],"iteration":68,"passed_time":0.08372875455,"remaining_time":1.129731456},
{"learn":[0.4730172985],"iteration":69,"passed_time":0.0850550303,"remaining_time":1.130016831},
{"learn":[0.4711896245],"iteration":70,"passed_time":0.08633895272,"remaining_time":1.129702635},
{"learn":[0.4697220854],"iteration":71,"passed_time":0.08757780542,"remaining_time":1.128780603},
{"learn":[0.4677889704],"iteration":72,"passed_time":0.08892730677,"remaining_time":1.129254978},
{"learn":[0.4659576416],"iteration":73,"passed_time":0.09024126234,"remaining_time":1.129235256},
{"learn":[0.4644286104],"iteration":74,"passed_time":0.09191612177,"remaining_time":1.133632169},
{"learn":[0.4626566721],"iteration":75,"passed_time":0.09367434967,"remaining_time":1.138882883},
{"learn":[0.4609444441],"iteration":76,"passed_time":0.09533509798,"remaining_time":1.142783058},
{"learn":[0.4593146775],"iteration":77,"passed_time":0.09678829361,"remaining_time":1.144087266},
{"learn":[0.4581379234],"iteration":78,"passed_time":0.09795038002,"remaining_time":1.141927848},
{"learn":[0.456654029],"iteration":79,"passed_time":0.09944241302,"remaining_time":1.14358775},
{"learn":[0.454704376],"iteration":80,"passed_time":0.1008337917,"remaining_time":1.144027834},
{"learn":[0.4532086949],"iteration":81,"passed_time":0.1022129237,"remaining_time":1.144286146},
{"learn":[0.4518479216],"iteration":82,"passed_time":0.1038361922,"remaining_time":1.147202268},
{"learn":[0.4504043214],"iteration":83,"passed_time":0.1053976174,"remaining_time":1.149335923},
{"learn":[0.4487408849],"iteration":84,"passed_time":0.1069607323,"remaining_time":1.151400824},
{"learn":[0.4477628605],"iteration":85,"passed_time":0.1078982315,"remaining_time":1.146732367},
{"learn":[0.4460927998],"iteration":86,"passed_time":0.1093412477,"remaining_time":1.147454703},
{"learn":[0.4443872874],"iteration":87,"passed_time":0.1109125896,"remaining_time":1.149457747},
{"learn":[0.4438520877],"iteration":88,"passed_time":0.1116003256,"remaining_time":1.142335917},
{"learn":[0.4422216815],"iteration":89,"passed_time":0.1131440305,"remaining_time":1.144011864},
{"learn":[0.4414257118],"iteration":90,"passed_time":0.1142253073,"remaining_time":1.14099785},
{"learn":[0.439991477],"iteration":91,"passed_time":0.1155481676,"remaining_time":1.140410176},
{"learn":[0.4389848538],"iteration":92,"passed_time":0.1169403319,"remaining_time":1.140482592},
{"learn":[0.4379120787],"iteration":93,"passed_time":0.1185794991,"remaining_time":1.142904534},
{"learn":[0.4365671124],"iteration":94,"passed_time":0.1200314168,"remaining_time":1.143457181},
{"learn":[0.4356143974],"iteration":95,"passed_time":0.1213731701,"remaining_time":1.142930686},
{"learn":[0.4347112964],"iteration":96,"passed_time":0.122470394,"remaining_time":1.140110987},
{"learn":[0.4338807888],"iteration":97,"passed_time":0.1241423976,"remaining_time":1.142616761},
{"learn":[0.4323702144],"iteration":98,"passed_time":0.1258106688,"remaining_time":1.145004168},
{"learn":[0.4309344263],"iteration":99,"passed_time":0.1273155723,"remaining_time":1.14584015},
{"learn":[0.4300675992],"iteration":100,"passed_time":0.1284120588,"remaining_time":1.142994464},
{"learn":[0.4286862676],"iteration":101,"passed_time":0.1301328168,"remaining_time":1.145679113},
{"learn":[0.4276141321],"iteration":102,"passed_time":0.1317699567,"remaining_time":1.147550011},
{"learn":[0.4268168375],"iteration":103,"passed_time":0.1331558773,"remaining_time":1.147189097},
{"learn":[0.4253476994],"iteration":104,"passed_time":0.1344863684,"remaining_time":1.146336188},
{"learn":[0.4240654129],"iteration":105,"passed_time":0.1358145659,"remaining_time":1.145454924},
{"learn":[0.4233034328],"iteration":106,"passed_time":0.1372292032,"remaining_time":1.145286714},
{"learn":[0.4229182626],"iteration":107,"passed_time":0.1381247861,"remaining_time":1.140808418},
{"learn":[0.4221161254],"iteration":108,"passed_time":0.1391730737,"remaining_time":1.137644116},
{"learn":[0.4217718433],"iteration":109,"passed_time":0.1398844081,"remaining_time":1.131792029},
{"learn":[0.420793362],"iteration":110,"passed_time":0.141340129,"remaining_time":1.131994367},
{"learn":[0.4200182703],"iteration":111,"passed_time":0.142950806,"remaining_time":1.133395676},
{"learn":[0.418880988],"iteration":112,"passed_time":0.1446327093,"remaining_time":1.135302771},
{"learn":[0.4185113964],"iteration":113,"passed_time":0.1454856633,"remaining_time":1.130704365},
{"learn":[0.4174006571],"iteration":114,"passed_time":0.1470718929,"remaining_time":1.131814133},
{"learn":[0.4164330945],"iteration":115,"passed_time":0.1485597629,"remaining_time":1.132127848},
{"learn":[0.4153486697],"iteration":116,"passed_time":0.1502161467,"remaining_time":1.133682543},
{"learn":[0.4144066908],"iteration":117,"passed_time":0.1518074013,"remaining_time":1.134695999},
{"learn":[0.413923709],"iteration":118,"passed_time":0.1527025388,"remaining_time":1.130512073},
{"learn":[0.4129431262],"iteration":119,"passed_time":0.1540835533,"remaining_time":1.129946058},
{"learn":[0.4123136326],"iteration":120,"passed_time":0.1554832006,"remaining_time":1.129501928},
{"learn":[0.4120434059],"iteration":121,"passed_time":0.1564322799,"remaining_time":1.125799523},
{"learn":[0.4112600909],"iteration":122,"passed_time":0.1580384859,"remaining_time":1.126827253},
{"learn":[0.4104269793],"iteration":123,"passed_time":0.159501514,"remaining_time":1.126801018},
{"learn":[0.4089999627],"iteration":124,"passed_time":0.160914809,"remaining_time":1.126403663},
{"learn":[0.408153374],"iteration":125,"passed_time":0.1625016805,"remaining_time":1.127194197},
{"learn":[0.4077199605],"iteration":126,"passed_time":0.1639733917,"remaining_time":1.127155677},
{"learn":[0.4066874795],"iteration":127,"passed_time":0.1653993997,"remaining_time":1.12678341},
{"learn":[0.4064261613],"iteration":128,"passed_time":0.1662579325,"remaining_time":1.12256325},
{"learn":[0.4057551401],"iteration":129,"passed_time":0.1675914366,"remaining_time":1.12157346},
{"learn":[0.4049814647],"iteration":130,"passed_time":0.1692145153,"remaining_time":1.122499342},
{"learn":[0.4042783269],"iteration":131,"passed_time":0.1707617571,"remaining_time":1.122887918},
{"learn":[0.4040634247],"iteration":132,"passed_time":0.1715742685,"remaining_time":1.118457826},
{"learn":[0.4034224642],"iteration":133,"passed_time":0.1728761868,"remaining_time":1.117244611},
{"learn":[0.4026312914],"iteration":134,"passed_time":0.1743969674,"remaining_time":1.117432421},
{"learn":[0.4019345952],"iteration":135,"passed_time":0.175974267,"remaining_time":1.117954167},
{"learn":[0.4012383558],"iteration":136,"passed_time":0.1774746399,"remaining_time":1.117960688},
{"learn":[0.4005947456],"iteration":137,"passed_time":0.1789603024,"remaining_time":1.117853483},
{"learn":[0.4001701492],"iteration":138,"passed_time":0.1802542218,"remaining_time":1.116538741},
{"learn":[0.3996007314],"iteration":139,"passed_time":0.181597335,"remaining_time":1.115526486},
{"learn":[0.3987890917],"iteration":140,"passed_time":0.1833584647,"remaining_time":1.117056178},
{"learn":[0.3983888912],"iteration":141,"passed_time":0.1846241016,"remaining_time":1.115545628},
{"learn":[0.3973963389],"iteration":142,"passed_time":0.1859533034,"remaining_time":1.114419448},
{"learn":[0.397002717],"iteration":143,"passed_time":0.1868463387,"remaining_time":1.11069768},
{"learn":[0.396366325],"iteration":144,"passed_time":0.188250195,"remaining_time":1.110027012},
{"learn":[0.395496711],"iteration":145,"passed_time":0.1898387699,"remaining_time":1.110426777},
{"learn":[0.3947839794],"iteration":146,"passed_time":0.1911286244,"remaining_time":1.109066099},
{"learn":[0.3939318628],"iteration":147,"passed_time":0.1924217445,"remaining_time":1.107725178},
{"learn":[0.3931775578],"iteration":148,"passed_time":0.193727268,"remaining_time":1.106455739},
{"learn":[0.392726921],"iteration":149,"passed_time":0.1950768579,"remaining_time":1.105435528},
{"learn":[0.392087194],"iteration":150,"passed_time":0.1965172966,"remaining_time":1.104921754},
{"learn":[0.3915090047],"iteration":151,"passed_time":0.197778789,"remaining_time":1.103397454},
{"learn":[0.3909545716],"iteration":152,"passed_time":0.199067505,"remaining_time":1.102027299},
{"learn":[0.3902683829],"iteration":153,"passed_time":0.2003989428,"remaining_time":1.100892894},
{"learn":[0.3894327129],"iteration":154,"passed_time":0.2017920845,"remaining_time":1.100092332},
{"learn":[0.3889175689],"iteration":155,"passed_time":0.2032606346,"remaining_time":1.099692151},
{"learn":[0.3881501523],"iteration":156,"passed_time":0.204510932,"remaining_time":1.098106469},
{"learn":[0.3874829229],"iteration":157,"passed_time":0.2057866653,"remaining_time":1.096660584},
{"learn":[0.3867156434],"iteration":158,"passed_time":0.2071223438,"remaining_time":1.095533907},
{"learn":[0.3860513836],"iteration":159,"passed_time":0.2085987787,"remaining_time":1.095143588},
{"learn":[0.3855459248],"iteration":160,"passed_time":0.2099175445,"remaining_time":1.093918136},
{"learn":[0.3848561727],"iteration":161,"passed_time":0.2112030648,"remaining_time":1.092519557},
{"learn":[0.3847386709],"iteration":162,"passed_time":0.2118402025,"remaining_time":1.087792941},
{"learn":[0.3842486536],"iteration":163,"passed_time":0.2131400835,"remaining_time":1.086494572},
{"learn":[0.3836579009],"iteration":164,"passed_time":0.2145667849,"remaining_time":1.085837972},
{"learn":[0.382904738],"iteration":165,"passed_time":0.2160402138,"remaining_time":1.085406857},
{"learn":[0.3827964646],"iteration":166,"passed_time":0.2166903141,"remaining_time":1.080856477},
{"learn":[0.3824038249],"iteration":167,"passed_time":0.2179613838,"remaining_time":1.079427805},
{"learn":[0.3816961414],"iteration":168,"passed_time":0.2192673663,"remaining_time":1.078172671},
{"learn":[0.3810010442],"iteration":169,"passed_time":0.2207719106,"remaining_time":1.077886387},
{"learn":[0.3806619244],"iteration":170,"passed_time":0.2223041139,"remaining_time":1.077719944},
{"learn":[0.3802456656],"iteration":171,"passed_time":0.2236852372,"remaining_time":1.076810328},
{"learn":[0.3797955085],"iteration":172,"passed_time":0.2249914798,"remaining_time":1.075537305},
{"learn":[0.3792017406],"iteration":173,"passed_time":0.226301227,"remaining_time":1.074280537},
{"learn":[0.3786142772],"iteration":174,"passed_time":0.2275956454,"remaining_time":1.0729509},
{"learn":[0.3782706803],"iteration":175,"passed_time":0.2290552225,"remaining_time":1.072394905},
{"learn":[0.3779398067],"iteration":176,"passed_time":0.2302974906,"remaining_time":1.070818276},
{"learn":[0.3774590178],"iteration":177,"passed_time":0.2315394192,"remaining_time":1.069243835},
{"learn":[0.3773104959],"iteration":178,"passed_time":0.2324489934,"remaining_time":1.066148735},
{"learn":[0.3769057497],"iteration":179,"passed_time":0.2338097524,"remaining_time":1.065133316},
{"learn":[0.3764004736],"iteration":180,"passed_time":0.2352602319,"remaining_time":1.064520055},
{"learn":[0.37586452],"iteration":181,"passed_time":0.2365682421,"remaining_time":1.063257264},
{"learn":[0.3754355608],"iteration":182,"passed_time":0.2378362159,"remaining_time":1.061815237},
{"learn":[0.3750652382],"iteration":183,"passed_time":0.2388663179,"remaining_time":1.059320192},
{"learn":[0.3748327472],"iteration":184,"passed_time":0.2398234245,"remaining_time":1.05651941},
{"learn":[0.3743996078],"iteration":185,"passed_time":0.2413638837,"remaining_time":1.056291405},
{"learn":[0.3737525255],"iteration":186,"passed_time":0.2427034617,"remaining_time":1.055176012},
{"learn":[0.3732906045],"iteration":187,"passed_time":0.243989661,"remaining_time":1.053827685},
{"learn":[0.3732186506],"iteration":188,"passed_time":0.2446297048,"remaining_time":1.049707358},
{"learn":[0.3728689319],"iteration":189,"passed_time":0.2458881413,"remaining_time":1.048259971},
{"learn":[0.3723118491],"iteration":190,"passed_time":0.2473085242,"remaining_time":1.047500503},
{"learn":[0.3720173636],"iteration":191,"passed_time":0.2486077657,"remaining_time":1.046224348},
{"learn":[0.3716391375],"iteration":192,"passed_time":0.2501215217,"remaining_time":1.045844912},
{"learn":[0.3712612997],"iteration":193,"passed_time":0.2516483851,"remaining_time":1.045508239},
{"learn":[0.3708903147],"iteration":194,"passed_time":0.2529998402,"remaining_time":1.044435238},
{"learn":[0.3705151495],"iteration":195,"passed_time":0.254394125,"remaining_time":1.043535084},
{"learn":[0.3699713838],"iteration":196,"passed_time":0.255909078,"remaining_time":1.043121775},
{"learn":[0.3695554448],"iteration":197,"passed_time":0.2571631204,"remaining_time":1.041640518},
{"learn":[0.3691577797],"iteration":198,"passed_time":0.2583997161,"remaining_time":1.040091319},
{"learn":[0.3688779134],"iteration":199,"passed_time":0.2596922273,"remaining_time":1.038768909},
{"learn":[0.3684310456],"iteration":200,"passed_time":0.2610978469,"remaining_time":1.037896416},
{"learn":[0.3679789469],"iteration":201,"passed_time":0.262392535,"remaining_time":1.03658041},
{"learn":[0.3676260303],"iteration":202,"passed_time":0.263648844,"remaining_time":1.035113934},
{"learn":[0.3669953489],"iteration":203,"passed_time":0.2648989516,"remaining_time":1.033625321},
{"learn":[0.366371566],"iteration":204,"passed_time":0.2661795984,"remaining_time":1.032257467},
{"learn":[0.3660259133],"iteration":205,"passed_time":0.2675208342,"remaining_time":1.031123992},
{"learn":[0.3658145516],"iteration":206,"passed_time":0.2684281204,"remaining_time":1.028326085},
{"learn":[0.3655662765],"iteration":207,"passed_time":0.2696829917,"remaining_time":1.026869853},
{"learn":[0.3649996912],"iteration":208,"passed_time":0.2709399502,"remaining_time":1.025423448},
{"learn":[0.3647559617],"iteration":209,"passed_time":0.2718430191,"remaining_time":1.022647548},
{"learn":[0.3643456191],"iteration":210,"passed_time":0.2731120245,"remaining_time":1.02125776},
{"learn":[0.364081377],"iteration":211,"passed_time":0.274456676,"remaining_time":1.020150286},
{"learn":[0.3635825882],"iteration":212,"passed_time":0.2757230818,"remaining_time":1.018751481},
{"learn":[0.3631097485],"iteration":213,"passed_time":0.2769694145,"remaining_time":1.017280186},
{"learn":[0.3629081406],"iteration":214,"passed_time":0.2781833306,"remaining_time":1.015692626},
{"learn":[0.3626433961],"iteration":215,"passed_time":0.2794841201,"remaining_time":1.014423843},
{"learn":[0.3623026317],"iteration":216,"passed_time":0.2809136347,"remaining_time":1.013619244},
{"learn":[0.3619843443],"iteration":217,"passed_time":0.2822053068,"remaining_time":1.012314449},
{"learn":[0.3614964057],"iteration":218,"passed_time":0.2835248149,"remaining_time":1.011109043},
{"learn":[0.3609678531],"iteration":219,"passed_time":0.2848438404,"remaining_time":1.009900889},
{"learn":[0.3607474687],"iteration":220,"passed_time":0.2859099009,"remaining_time":1.007800058},
{"learn":[0.3605422745],"iteration":221,"passed_time":0.2869390641,"remaining_time":1.005579243},
{"learn":[0.3598943699],"iteration":222,"passed_time":0.2883720811,"remaining_time":1.004776265},
{"learn":[0.3594787049],"iteration":223,"passed_time":0.2896629742,"remaining_time":1.003475303},
{"learn":[0.3590475756],"iteration":224,"passed_time":0.2909004986,"remaining_time":1.001990606},
{"learn":[0.3586637988],"iteration":225,"passed_time":0.2923176721,"remaining_time":1.001123355},
{"learn":[0.3583322171],"iteration":226,"passed_time":0.2936032423,"remaining_time":0.9998031116},
{"learn":[0.3580013663],"iteration":227,"passed_time":0.294948303,"remaining_time":0.9986846048},
{"learn":[0.3575427347],"iteration":228,"passed_time":0.2963781269,"remaining_time":0.9978495014},
{"learn":[0.3572742668],"iteration":229,"passed_time":0.2976488469,"remaining_time":0.9964765745},
{"learn":[0.3569120533],"iteration":230,"passed_time":0.2989692788,"remaining_time":0.9952700235},
{"learn":[0.3564562769],"iteration":231,"passed_time":0.3003223604,"remaining_time":0.9941705724},
{"learn":[0.3561480859],"iteration":232,"passed_time":0.3015901744,"remaining_time":0.9927882564},
{"learn":[0.3556239419],"iteration":233,"passed_time":0.3028348792,"remaining_time":0.9913312714},
{"learn":[0.3550939274],"iteration":234,"passed_time":0.3041015348,"remaining_time":0.9899475493},
{"learn":[0.3549595679],"iteration":235,"passed_time":0.3053417157,"remaining_time":0.9884791135},
{"learn":[0.3548640862],"iteration":236,"passed_time":0.30622053,"remaining_time":0.9858492169},
{"learn":[0.3545024209],"iteration":237,"passed_time":0.3075861615,"remaining_time":0.9847926682},
{"learn":[0.3541231898],"iteration":238,"passed_time":0.3088702636,"remaining_time":0.9834739357},
{"learn":[0.353823382],"iteration":239,"passed_time":0.3101008274,"remaining_time":0.9819859536},
{"learn":[0.3535328711],"iteration":240,"passed_time":0.3114604236,"remaining_time":0.9809064794},
{"learn":[0.3532058122],"iteration":241,"passed_time":0.3125166776,"remaining_time":0.9788745521},
{"learn":[0.3528703701],"iteration":242,"passed_time":0.3139764644,"remaining_time":0.9781077513},
{"learn":[0.3525333062],"iteration":243,"passed_time":0.3152276606,"remaining_time":0.9766889812},
{"learn":[0.3521944377],"iteration":244,"passed_time":0.3164709274,"remaining_time":0.9752471436},
{"learn":[0.3520114236],"iteration":245,"passed_time":0.3176981956,"remaining_time":0.9737578841},
{"learn":[0.3517416766],"iteration":246,"passed_time":0.3189451974,"remaining_time":0.9723309055},
{"learn":[0.351502607],"iteration":247,"passed_time":0.3202845061,"remaining_time":0.9711852765},
{"learn":[0.3511792942],"iteration":248,"passed_time":0.3215586216,"remaining_time":0.9698414651},
{"learn":[0.3509979248],"iteration":249,"passed_time":0.3226142924,"remaining_time":0.9678428771},
{"learn":[0.3509737574],"iteration":250,"passed_time":0.3232871422,"remaining_time":0.9647094404},
{"learn":[0.350829804],"iteration":251,"passed_time":0.3245406254,"remaining_time":0.9633189991},
{"learn":[0.3505608108],"iteration":252,"passed_time":0.3258170978,"remaining_time":0.9619975179},
{"learn":[0.3502589928],"iteration":253,"passed_time":0.3271159702,"remaining_time":0.9607421801},
{"learn":[0.3498592034],"iteration":254,"passed_time":0.3283676457,"remaining_time":0.959348612},
{"learn":[0.349597771],"iteration":255,"passed_time":0.3295912988,"remaining_time":0.957874712},
{"learn":[0.3493558004],"iteration":256,"passed_time":0.330849905,"remaining_time":0.9565038111},
{"learn":[0.3493347625],"iteration":257,"passed_time":0.3315104014,"remaining_time":0.9534136352},
{"learn":[0.3489992519],"iteration":258,"passed_time":0.3327638247,"remaining_time":0.9520385872},
{"learn":[0.3487430047],"iteration":259,"passed_time":0.3341962654,"remaining_time":0.9511739861},
{"learn":[0.3484276412],"iteration":260,"passed_time":0.335545039,"remaining_time":0.9500681374},
{"learn":[0.3481542622],"iteration":261,"passed_time":0.3368104762,"remaining_time":0.9487256925},
{"learn":[0.347717011],"iteration":262,"passed_time":0.33807842,"remaining_time":0.9473908575},
{"learn":[0.347383739],"iteration":263,"passed_time":0.3393408911,"remaining_time":0.9460412721},
{"learn":[0.3469307037],"iteration":264,"passed_time":0.3407244019,"remaining_time":0.9450280582},
{"learn":[0.3467837579],"iteration":265,"passed_time":0.3419737206,"remaining_time":0.9436417705},
{"learn":[0.3464782852],"iteration":266,"passed_time":0.3432166379,"remaining_time":0.9422389348},
{"learn":[0.3459986384],"iteration":267,"passed_time":0.3444759033,"remaining_time":0.9408819449},
{"learn":[0.345703856],"iteration":268,"passed_time":0.3457905929,"remaining_time":0.9396762952},
{"learn":[0.3454965374],"iteration":269,"passed_time":0.3471376029,"remaining_time":0.9385572227},
{"learn":[0.3453083153],"iteration":270,"passed_time":0.3484018616,"remaining_time":0.9372138639},
{"learn":[0.3448685058],"iteration":271,"passed_time":0.3496703048,"remaining_time":0.9358822862},
{"learn":[0.3444096457],"iteration":272,"passed_time":0.3509136015,"remaining_time":0.9344842062},
{"learn":[0.3441414291],"iteration":273,"passed_time":0.3523191143,"remaining_time":0.9335170692},
{"learn":[0.3438804307],"iteration":274,"passed_time":0.3535951472,"remaining_time":0.9322053882},
{"learn":[0.3436459981],"iteration":275,"passed_time":0.3548752914,"remaining_time":0.9309047498},
{"learn":[0.3433924235],"iteration":276,"passed_time":0.3562187774,"remaining_time":0.9297695887},
{"learn":[0.3430594484],"iteration":277,"passed_time":0.3574634024,"remaining_time":0.9283761746},
{"learn":[0.3427324809],"iteration":278,"passed_time":0.3587119921,"remaining_time":0.9269940728},
{"learn":[0.3423869424],"iteration":279,"passed_time":0.360077031,"remaining_time":0.9259123654},
{"learn":[0.3421602078],"iteration":280,"passed_time":0.3613305141,"remaining_time":0.9245432016},
{"learn":[0.3419276483],"iteration":281,"passed_time":0.3625725326,"remaining_time":0.9231456681},
{"learn":[0.341645612],"iteration":282,"passed_time":0.3638421342,"remaining_time":0.9218191173},
{"learn":[0.3412663808],"iteration":283,"passed_time":0.3651446434,"remaining_time":0.9205759319},
{"learn":[0.3410034637],"iteration":284,"passed_time":0.3664990219,"remaining_time":0.9194624584},
{"learn":[0.3406888311],"iteration":285,"passed_time":0.3677491595,"remaining_time":0.9180870625},
{"learn":[0.34045883],"iteration":286,"passed_time":0.3690125693,"remaining_time":0.916745512},
{"learn":[0.3402419176],"iteration":287,"passed_time":0.3702545479,"remaining_time":0.9153515211},
{"learn":[0.3400730202],"iteration":288,"passed_time":0.3715452412,"remaining_time":0.9140784308},
{"learn":[0.3397178878],"iteration":289,"passed_time":0.3730687731,"remaining_time":0.913375272},
{"learn":[0.3394453311],"iteration":290,"passed_time":0.3744106679,"remaining_time":0.9122239298},
{"learn":[0.3393126848],"iteration":291,"passed_time":0.3756594673,"remaining_time":0.9108455578},
{"learn":[0.339300898],"iteration":292,"passed_time":0.3762840518,"remaining_time":0.9079618588},
{"learn":[0.3388881112],"iteration":293,"passed_time":0.3775511367,"remaining_time":0.9066364032},
{"learn":[0.3388675758],"iteration":294,"passed_time":0.3783258104,"remaining_time":0.9041345638},
{"learn":[0.3385906105],"iteration":295,"passed_time":0.3798296253,"remaining_time":0.9033785683},
{"learn":[0.3383592845],"iteration":296,"passed_time":0.3810896497,"remaining_time":0.902040484},
{"learn":[0.338131956],"iteration":297,"passed_time":0.3823025371,"remaining_time":0.9005918828},
{"learn":[0.337806222],"iteration":298,"passed_time":0.3835526947,"remaining_time":0.8992322375},
{"learn":[0.3375881675],"iteration":299,"passed_time":0.3848869132,"remaining_time":0.8980694641},
{"learn":[0.3375283887],"iteration":300,"passed_time":0.3859379471,"remaining_time":0.8962479238},
{"learn":[0.3373084611],"iteration":301,"passed_time":0.3872876216,"remaining_time":0.8951217214},
{"learn":[0.3371337845],"iteration":302,"passed_time":0.3886199423,"remaining_time":0.8939541246},
{"learn":[0.3368511086],"iteration":303,"passed_time":0.3899214212,"remaining_time":0.8927148327},
{"learn":[0.3367535254],"iteration":304,"passed_time":0.3908008747,"remaining_time":0.8905134686},
{"learn":[0.3365764504],"iteration":305,"passed_time":0.3920858227,"remaining_time":0.8892403953},
{"learn":[0.3364427304],"iteration":306,"passed_time":0.393505157,"remaining_time":0.8882705987},
{"learn":[0.3361722295],"iteration":307,"passed_time":0.3947761068,"remaining_time":0.8869644996},
{"learn":[0.3358946246],"iteration":308,"passed_time":0.3960320067,"remaining_time":0.8856249728},
{"learn":[0.3354843962],"iteration":309,"passed_time":0.3972851902,"remaining_time":0.8842799395},
{"learn":[0.3354297569],"iteration":310,"passed_time":0.398298215,"remaining_time":0.882403441},
{"learn":[0.3352762554],"iteration":311,"passed_time":0.3996077798,"remaining_time":0.8811863862},
{"learn":[0.3351965122],"iteration":312,"passed_time":0.4008764826,"remaining_time":0.8798790528},
{"learn":[0.33478987],"iteration":313,"passed_time":0.4023265727,"remaining_time":0.8789682448},
{"learn":[0.3345722495],"iteration":314,"passed_time":0.4040001838,"remaining_time":0.8785400822},
{"learn":[0.3342026351],"iteration":315,"passed_time":0.4056633522,"remaining_time":0.8780814332},
{"learn":[0.3340274103],"iteration":316,"passed_time":0.4071236456,"remaining_time":0.8771780756},
{"learn":[0.3338061121],"iteration":317,"passed_time":0.4089893028,"remaining_time":0.8771405803},
{"learn":[0.3334197541],"iteration":318,"passed_time":0.4104226034,"remaining_time":0.8761686299},
{"learn":[0.3330220891],"iteration":319,"passed_time":0.4118324973,"remaining_time":0.8751440568},
{"learn":[0.3328580571],"iteration":320,"passed_time":0.4132615652,"remaining_time":0.8741576411},
{"learn":[0.3326230991],"iteration":321,"passed_time":0.4145311967,"remaining_time":0.8728327683},
{"learn":[0.3323529181],"iteration":322,"passed_time":0.4157881752,"remaining_time":0.8714817171},
{"learn":[0.3318718094],"iteration":323,"passed_time":0.4170359959,"remaining_time":0.8701121396},
{"learn":[0.3314668575],"iteration":324,"passed_time":0.4183116394,"remaining_time":0.8688010972},
{"learn":[0.3313687719],"iteration":325,"passed_time":0.4196863913,"remaining_time":0.8676951771},
{"learn":[0.3313588125],"iteration":326,"passed_time":0.4204001165,"remaining_time":0.8652271511},
{"learn":[0.3311128902],"iteration":327,"passed_time":0.4216347349,"remaining_time":0.8638370178},
{"learn":[0.3308286838],"iteration":328,"passed_time":0.4228838239,"remaining_time":0.8624773429},
{"learn":[0.3304520567],"iteration":329,"passed_time":0.4241170441,"remaining_time":0.8610861199},
{"learn":[0.3302070937],"iteration":330,"passed_time":0.4253892512,"remaining_time":0.8597746497},
{"learn":[0.3300898889],"iteration":331,"passed_time":0.4267615354,"remaining_time":0.8586647761},
{"learn":[0.3298074871],"iteration":332,"passed_time":0.428037838,"remaining_time":0.857361075},
{"learn":[0.3294224996],"iteration":333,"passed_time":0.4293030854,"remaining_time":0.8560354937},
{"learn":[0.3292276531],"iteration":334,"passed_time":0.4305250707,"remaining_time":0.8546243941},
{"learn":[0.3289414823],"iteration":335,"passed_time":0.4318833543,"remaining_time":0.8534837716},
{"learn":[0.3287436662],"iteration":336,"passed_time":0.4331794205,"remaining_time":0.8522194533},
{"learn":[0.3285166575],"iteration":337,"passed_time":0.4344218584,"remaining_time":0.850849912},
{"learn":[0.3283358591],"iteration":338,"passed_time":0.4358305838,"remaining_time":0.8498053567},
{"learn":[0.3281523882],"iteration":339,"passed_time":0.4370873715,"remaining_time":0.8484637212},
{"learn":[0.3278746462],"iteration":340,"passed_time":0.4383893302,"remaining_time":0.8472098785},
{"learn":[0.3277035787],"iteration":341,"passed_time":0.4396869439,"remaining_time":0.845947395},
{"learn":[0.3272708276],"iteration":342,"passed_time":0.4409467486,"remaining_time":0.8446122852},
{"learn":[0.3271338411],"iteration":343,"passed_time":0.4421803683,"remaining_time":0.8432276791},
{"learn":[0.326864688],"iteration":344,"passed_time":0.4434369872,"remaining_time":0.8418876135},
{"learn":[0.3266510193],"iteration":345,"passed_time":0.444769455,"remaining_time":0.8406913977},
{"learn":[0.3264406627],"iteration":346,"passed_time":0.4461588564,"remaining_time":0.8396015366},
{"learn":[0.3261385706],"iteration":347,"passed_time":0.4474421696,"remaining_time":0.8383111913},
{"learn":[0.325701548],"iteration":348,"passed_time":0.4486713153,"remaining_time":0.836919846},
{"learn":[0.325526483],"iteration":349,"passed_time":0.4499514125,"remaining_time":0.8356240517},
{"learn":[0.3252358808],"iteration":350,"passed_time":0.4512648764,"remaining_time":0.834390042},
{"learn":[0.3249431313],"iteration":351,"passed_time":0.4527381105,"remaining_time":0.8334497035},
{"learn":[0.3246070953],"iteration":352,"passed_time":0.4539792701,"remaining_time":0.8320809852},
{"learn":[0.3244872864],"iteration":353,"passed_time":0.455220979,"remaining_time":0.83071399},
{"learn":[0.3244820783],"iteration":354,"passed_time":0.4558586859,"remaining_time":0.8282502885},
{"learn":[0.3241559103],"iteration":355,"passed_time":0.4571681884,"remaining_time":0.8270121162},
{"learn":[0.3239710916],"iteration":356,"passed_time":0.4586504262,"remaining_time":0.8260846612},
{"learn":[0.3236757153],"iteration":357,"passed_time":0.4599788092,"remaining_time":0.8248781997},
{"learn":[0.3232920298],"iteration":358,"passed_time":0.461270601,"remaining_time":0.823605725},
{"learn":[0.3232245531],"iteration":359,"passed_time":0.4625039012,"remaining_time":0.8222291577},
{"learn":[0.3230325847],"iteration":360,"passed_time":0.4638955828,"remaining_time":0.8211337324},
{"learn":[0.3230196102],"iteration":361,"passed_time":0.4647848631,"remaining_time":0.8191512228},
{"learn":[0.3228067638],"iteration":362,"passed_time":0.4661127074,"remaining_time":0.8179443379},
{"learn":[0.3225872474],"iteration":363,"passed_time":0.4673734409,"remaining_time":0.8166195286},
{"learn":[0.3224497355],"iteration":364,"passed_time":0.4686289613,"remaining_time":0.8152860011},
{"learn":[0.3222493155],"iteration":365,"passed_time":0.4699145814,"remaining_time":0.81400504},
{"learn":[0.3221280446],"iteration":366,"passed_time":0.471342686,"remaining_time":0.8129698098},
{"learn":[0.3219506041],"iteration":367,"passed_time":0.4729830405,"remaining_time":0.8122969609},
{"learn":[0.3216948595],"iteration":368,"passed_time":0.4744740013,"remaining_time":0.8113634006},
{"learn":[0.3214096481],"iteration":369,"passed_time":0.4757706923,"remaining_time":0.8100960437},
{"learn":[0.3211915707],"iteration":370,"passed_time":0.4770645215,"remaining_time":0.8088236766},
{"learn":[0.3210625791],"iteration":371,"passed_time":0.4783180988,"remaining_time":0.8074832421},
{"learn":[0.3209086435],"iteration":372,"passed_time":0.4795744781,"remaining_time":0.8061479833},
{"learn":[0.3206151403],"iteration":373,"passed_time":0.4808177848,"remaining_time":0.8047912655},
{"learn":[0.3201478513],"iteration":374,"passed_time":0.4820698698,"remaining_time":0.8034497831},
{"learn":[0.3201298742],"iteration":375,"passed_time":0.4828216641,"remaining_time":0.8012785064},
{"learn":[0.3199099923],"iteration":376,"passed_time":0.4841197076,"remaining_time":0.8000174479},
{"learn":[0.3197103261],"iteration":377,"passed_time":0.4854484701,"remaining_time":0.7988067417},
{"learn":[0.3196806765],"iteration":378,"passed_time":0.486335823,"remaining_time":0.7968721532},
{"learn":[0.3195081243],"iteration":379,"passed_time":0.4875914732,"remaining_time":0.7955439826},
{"learn":[0.3193154249],"iteration":380,"passed_time":0.4888310649,"remaining_time":0.7941901029},
{"learn":[0.3190645001],"iteration":381,"passed_time":0.4900709163,"remaining_time":0.7928372416},
{"learn":[0.3188228036],"iteration":382,"passed_time":0.4915607799,"remaining_time":0.7918877316},
{"learn":[0.318764738],"iteration":383,"passed_time":0.4928252783,"remaining_time":0.7905738839},
{"learn":[0.3184679682],"iteration":384,"passed_time":0.4940898765,"remaining_time":0.7892604521},
{"learn":[0.3180898564],"iteration":385,"passed_time":0.4953490021,"remaining_time":0.7879385682},
{"learn":[0.3179391187],"iteration":386,"passed_time":0.4967573538,"remaining_time":0.7868533795},
{"learn":[0.317603471],"iteration":387,"passed_time":0.4980684042,"remaining_time":0.7856130499},
{"learn":[0.3173550817],"iteration":388,"passed_time":0.4993746667,"remaining_time":0.7843648364},
{"learn":[0.3173278991],"iteration":389,"passed_time":0.5002529818,"remaining_time":0.7824469715},
{"learn":[0.317172593],"iteration":390,"passed_time":0.5014894976,"remaining_time":0.7810923377},
{"learn":[0.3169481654],"iteration":391,"passed_time":0.5027400247,"remaining_time":0.7797600383},
{"learn":[0.3167014208],"iteration":392,"passed_time":0.5039712276,"remaining_time":0.7783983083},
{"learn":[0.3163262099],"iteration":393,"passed_time":0.5052839462,"remaining_time":0.7771626177},
{"learn":[0.3162724843],"iteration":394,"passed_time":0.5065396663,"remaining_time":0.7758392357},
{"learn":[0.3160666277],"iteration":395,"passed_time":0.5078234,"remaining_time":0.7745589232},
{"learn":[0.3157975431],"iteration":396,"passed_time":0.509092692,"remaining_time":0.7732566581},
{"learn":[0.3155944276],"iteration":397,"passed_time":0.5103262617,"remaining_time":0.7719005265},
{"learn":[0.3154200023],"iteration":398,"passed_time":0.5116116465,"remaining_time":0.7706230565},
{"learn":[0.3150987454],"iteration":399,"passed_time":0.5128784518,"remaining_time":0.7693176778},
{"learn":[0.314948259],"iteration":400,"passed_time":0.5141027141,"remaining_time":0.767948942},
{"learn":[0.3146966032],"iteration":401,"passed_time":0.5153358644,"remaining_time":0.7665941465},
{"learn":[0.3145264037],"iteration":402,"passed_time":0.5165924933,"remaining_time":0.7652747358},
{"learn":[0.3143071614],"iteration":403,"passed_time":0.5178788581,"remaining_time":0.7639995036},
{"learn":[0.3141073809],"iteration":404,"passed_time":0.5192069058,"remaining_time":0.7627854543},
{"learn":[0.3139658945],"iteration":405,"passed_time":0.5204692771,"remaining_time":0.7614747552},
{"learn":[0.3137758449],"iteration":406,"passed_time":0.5216965653,"remaining_time":0.7601131774},
{"learn":[0.3136820536],"iteration":407,"passed_time":0.5227021001,"remaining_time":0.7584304982},
{"learn":[0.313432842],"iteration":408,"passed_time":0.5239532064,"remaining_time":0.757105978},
{"learn":[0.3129809031],"iteration":409,"passed_time":0.5252520988,"remaining_time":0.7558505812},
{"learn":[0.3128634698],"iteration":410,"passed_time":0.5264819036,"remaining_time":0.754495964},
{"learn":[0.3126482021],"iteration":411,"passed_time":0.5277485192,"remaining_time":0.7531944885},
{"learn":[0.3125526748],"iteration":412,"passed_time":0.5290024917,"remaining_time":0.7518752121},
{"learn":[0.3125195303],"iteration":413,"passed_time":0.5297711733,"remaining_time":0.749869342},
{"learn":[0.3123744119],"iteration":414,"passed_time":0.5310161878,"remaining_time":0.7485408912},
{"learn":[0.3122626664],"iteration":415,"passed_time":0.5322639586,"remaining_time":0.7472167111},
{"learn":[0.3120772996],"iteration":416,"passed_time":0.5335041695,"remaining_time":0.745882328},
{"learn":[0.3119304451],"iteration":417,"passed_time":0.5347384483,"remaining_time":0.7445401361},
{"learn":[0.3117292027],"iteration":418,"passed_time":0.5359885759,"remaining_time":0.7432204358},
{"learn":[0.3114605749],"iteration":419,"passed_time":0.5372182808,"remaining_time":0.741872864},
{"learn":[0.3111906451],"iteration":420,"passed_time":0.5384989047,"remaining_time":0.7405958808},
{"learn":[0.3109377558],"iteration":421,"passed_time":0.5397428406,"remaining_time":0.73926863},
{"learn":[0.3108156398],"iteration":422,"passed_time":0.5409966333,"remaining_time":0.7379552185},
{"learn":[0.3106750671],"iteration":423,"passed_time":0.5422498268,"remaining_time":0.7366412742},
{"learn":[0.310515695],"iteration":424,"passed_time":0.543478643,"remaining_time":0.7352946346},
{"learn":[0.310324983],"iteration":425,"passed_time":0.5447603084,"remaining_time":0.7340197582},
{"learn":[0.310123101],"iteration":426,"passed_time":0.5459899834,"remaining_time":0.7326750831},
{"learn":[0.3099423254],"iteration":427,"passed_time":0.5472551309,"remaining_time":0.7313783525},
{"learn":[0.3097207532],"iteration":428,"passed_time":0.5484940136,"remaining_time":0.7300468106},
{"learn":[0.3095610613],"iteration":429,"passed_time":0.5498440372,"remaining_time":0.7288630261},
{"learn":[0.3093105933],"iteration":430,"passed_time":0.5511852763,"remaining_time":0.7276668729},
{"learn":[0.3091810078],"iteration":431,"passed_time":0.5524872046,"remaining_time":0.7264183616},
{"learn":[0.3091262086],"iteration":432,"passed_time":0.5533723006,"remaining_time":0.7246237746},
{"learn":[0.3089694634],"iteration":433,"passed_time":0.5546249248,"remaining_time":0.72331269},
{"learn":[0.3086462421],"iteration":434,"passed_time":0.5558907515,"remaining_time":0.722019022},
{"learn":[0.3083799442],"iteration":435,"passed_time":0.5571494676,"remaining_time":0.7207162838},
{"learn":[0.3081069992],"iteration":436,"passed_time":0.5585461089,"remaining_time":0.71959144},
{"learn":[0.3079226602],"iteration":437,"passed_time":0.5597876979,"remaining_time":0.7182664069},
{"learn":[0.307775486],"iteration":438,"passed_time":0.561065928,"remaining_time":0.7169885776},
{"learn":[0.3075225967],"iteration":439,"passed_time":0.5623189427,"remaining_time":0.7156786544},
{"learn":[0.3073729098],"iteration":440,"passed_time":0.5636276979,"remaining_time":0.7144396443},
{"learn":[0.3069506205],"iteration":441,"passed_time":0.5650010337,"remaining_time":0.713281848},
{"learn":[0.3067611192],"iteration":442,"passed_time":0.5662495435,"remaining_time":0.7119661303},
{"learn":[0.3065076131],"iteration":443,"passed_time":0.5674933496,"remaining_time":0.7106448251},
{"learn":[0.3063800378],"iteration":444,"passed_time":0.5687773222,"remaining_time":0.7093739637},
{"learn":[0.3061288617],"iteration":445,"passed_time":0.5701269135,"remaining_time":0.7081845517},
{"learn":[0.306035116],"iteration":446,"passed_time":0.5714447439,"remaining_time":0.7069551306},
{"learn":[0.3058898606],"iteration":447,"passed_time":0.5727065658,"remaining_time":0.7056563043},
{"learn":[0.3057296662],"iteration":448,"passed_time":0.5739451589,"remaining_time":0.7043291371},
{"learn":[0.3056836614],"iteration":449,"passed_time":0.5748106211,"remaining_time":0.7025463147},
{"learn":[0.3053052754],"iteration":450,"passed_time":0.5761625222,"remaining_time":0.7013597},
{"learn":[0.3051748676],"iteration":451,"passed_time":0.5774644076,"remaining_time":0.7001117154},
{"learn":[0.3051731772],"iteration":452,"passed_time":0.5781183528,"remaining_time":0.6980811015},
{"learn":[0.3051033705],"iteration":453,"passed_time":0.5794216027,"remaining_time":0.6968374341},
{"learn":[0.305048914],"iteration":454,"passed_time":0.5803236659,"remaining_time":0.6951129625},
{"learn":[0.3049467167],"iteration":455,"passed_time":0.5815607211,"remaining_time":0.6937917374},
{"learn":[0.3046345968],"iteration":456,"passed_time":0.5828520536,"remaining_time":0.6925353722},
{"learn":[0.3045164554],"iteration":457,"passed_time":0.5842037653,"remaining_time":0.6913503074},
{"learn":[0.3043547305],"iteration":458,"passed_time":0.5854776012,"remaining_time":0.6900727282},
{"learn":[0.3041672849],"iteration":459,"passed_time":0.5867295264,"remaining_time":0.688769444},
{"learn":[0.3040267122],"iteration":460,"passed_time":0.5879890312,"remaining_time":0.6874752447},
{"learn":[0.3038271144],"iteration":461,"passed_time":0.589288839,"remaining_time":0.6862281285},
{"learn":[0.3034863501],"iteration":462,"passed_time":0.5905896921,"remaining_time":0.6849819971},
{"learn":[0.3033017827],"iteration":463,"passed_time":0.5919685974,"remaining_time":0.6838257936},
{"learn":[0.3030449645],"iteration":464,"passed_time":0.5932102064,"remaining_time":0.6825106676},
{"learn":[0.3027645271],"iteration":465,"passed_time":0.5944679439,"remaining_time":0.6812143391},
{"learn":[0.3026149087],"iteration":466,"passed_time":0.5957201387,"remaining_time":0.67991185},
{"learn":[0.3024282855],"iteration":467,"passed_time":0.5970393939,"remaining_time":0.6786858067},
{"learn":[0.3020688588],"iteration":468,"passed_time":0.5983435589,"remaining_time":0.677442281},
{"learn":[0.3019510829],"iteration":469,"passed_time":0.59958357,"remaining_time":0.6761261535},
{"learn":[0.3017138635],"iteration":470,"passed_time":0.6008046965,"remaining_time":0.6747891389},
{"learn":[0.3014805959],"iteration":471,"passed_time":0.6020443281,"remaining_time":0.6734733162},
{"learn":[0.3013228],"iteration":472,"passed_time":0.603343591,"remaining_time":0.6722242547},
{"learn":[0.3012282549],"iteration":473,"passed_time":0.60476411,"remaining_time":0.6711095398},
{"learn":[0.3010477306],"iteration":474,"passed_time":0.6060159853,"remaining_time":0.6698071417},
{"learn":[0.3009321019],"iteration":475,"passed_time":0.6073335228,"remaining_time":0.6685772393},
{"learn":[0.3007239382],"iteration":476,"passed_time":0.6085907808,"remaining_time":0.6672808771},
{"learn":[0.3004625058],"iteration":477,"passed_time":0.6100269765,"remaining_time":0.6661800874},
{"learn":[0.3003088214],"iteration":478,"passed_time":0.6117567365,"remaining_time":0.6653972019},
{"learn":[0.2999582805],"iteration":479,"passed_time":0.6133540227,"remaining_time":0.664466858},
{"learn":[0.299804185],"iteration":480,"passed_time":0.6147272557,"remaining_time":0.6632919869},
{"learn":[0.299569227],"iteration":481,"passed_time":0.6161209412,"remaining_time":0.662138273},
{"learn":[0.2993731013],"iteration":482,"passed_time":0.6176286976,"remaining_time":0.6611056659},
{"learn":[0.2991409073],"iteration":483,"passed_time":0.6189177431,"remaining_time":0.6598379245},
{"learn":[0.2990713062],"iteration":484,"passed_time":0.619935941,"remaining_time":0.6582824941},
{"learn":[0.2990073472],"iteration":485,"passed_time":0.6211526733,"remaining_time":0.6569392471},
{"learn":[0.298836394],"iteration":486,"passed_time":0.6224045642,"remaining_time":0.6556335553},
{"learn":[0.2983940947],"iteration":487,"passed_time":0.623732612,"remaining_time":0.6544079863},
{"learn":[0.2983109708],"iteration":488,"passed_time":0.6250035118,"remaining_time":0.6531222792},
{"learn":[0.2981180659],"iteration":489,"passed_time":0.6263154967,"remaining_time":0.6518793945},
{"learn":[0.2980355817],"iteration":490,"passed_time":0.6275386504,"remaining_time":0.6505441406},
{"learn":[0.2978567706],"iteration":491,"passed_time":0.6288006821,"remaining_time":0.6492494847},
{"learn":[0.2975922088],"iteration":492,"passed_time":0.6300594282,"remaining_time":0.6479515823},
{"learn":[0.2974315575],"iteration":493,"passed_time":0.631432002,"remaining_time":0.6467704312},
{"learn":[0.2971264731],"iteration":494,"passed_time":0.632682549,"remaining_time":0.6454640147},
{"learn":[0.2970700749],"iteration":495,"passed_time":0.6339304696,"remaining_time":0.6441551546},
{"learn":[0.2968071121],"iteration":496,"passed_time":0.6351978042,"remaining_time":0.6428661882},
{"learn":[0.29641381],"iteration":497,"passed_time":0.6364502887,"remaining_time":0.6415623392},
{"learn":[0.2962540952],"iteration":498,"passed_time":0.6377041913,"remaining_time":0.6402601199},
{"learn":[0.2959904928],"iteration":499,"passed_time":0.638959462,"remaining_time":0.638959462},
{"learn":[0.2958492348],"iteration":500,"passed_time":0.6403086671,"remaining_time":0.6377525447},
{"learn":[0.2956283021],"iteration":501,"passed_time":0.6415793172,"remaining_time":0.6364671314},
{"learn":[0.2954473438],"iteration":502,"passed_time":0.6428294249,"remaining_time":0.6351614795},
{"learn":[0.2953493495],"iteration":503,"passed_time":0.6441098819,"remaining_time":0.6338859156},
{"learn":[0.2952662028],"iteration":504,"passed_time":0.6453475862,"remaining_time":0.6325684261},
{"learn":[0.2950239124],"iteration":505,"passed_time":0.6466026971,"remaining_time":0.6312682458},
{"learn":[0.2948032996],"iteration":506,"passed_time":0.6478422189,"remaining_time":0.6299530847},
{"learn":[0.2944823396],"iteration":507,"passed_time":0.6490773366,"remaining_time":0.628633956},
{"learn":[0.2943625536],"iteration":508,"passed_time":0.6503210429,"remaining_time":0.6273234421},
{"learn":[0.2941624533],"iteration":509,"passed_time":0.6515584875,"remaining_time":0.6260071742},
{"learn":[0.293913333],"iteration":510,"passed_time":0.6528006457,"remaining_time":0.6246957256},
{"learn":[0.293712616],"iteration":511,"passed_time":0.6540440723,"remaining_time":0.6233857564},
{"learn":[0.2936031776],"iteration":512,"passed_time":0.6553017498,"remaining_time":0.6220895754},
{"learn":[0.2933852601],"iteration":513,"passed_time":0.6566330988,"remaining_time":0.6208632024},
{"learn":[0.2932809156],"iteration":514,"passed_time":0.6578585195,"remaining_time":0.619536664},
{"learn":[0.2932285606],"iteration":515,"passed_time":0.658872543,"remaining_time":0.6180122302},
{"learn":[0.293082163],"iteration":516,"passed_time":0.6600963558,"remaining_time":0.6166857637},
{"learn":[0.2929456791],"iteration":517,"passed_time":0.6613402418,"remaining_time":0.6153783717},
{"learn":[0.2928413117],"iteration":518,"passed_time":0.6625920871,"remaining_time":0.6140786009},
{"learn":[0.2927473148],"iteration":519,"passed_time":0.6638782212,"remaining_time":0.6128106657},
{"learn":[0.2926020137],"iteration":520,"passed_time":0.6651572502,"remaining_time":0.6115361283},
{"learn":[0.2923933931],"iteration":521,"passed_time":0.666407987,"remaining_time":0.6102356662},
{"learn":[0.2922807339],"iteration":522,"passed_time":0.6676546392,"remaining_time":0.6089316691},
{"learn":[0.2921127959],"iteration":523,"passed_time":0.6689014713,"remaining_time":0.6076280541},
{"learn":[0.2919774312],"iteration":524,"passed_time":0.6701368986,"remaining_time":0.6063143368},
{"learn":[0.2918694319],"iteration":525,"passed_time":0.6713576055,"remaining_time":0.6049876521},
{"learn":[0.2915094113],"iteration":526,"passed_time":0.672625799,"remaining_time":0.6037039904},
{"learn":[0.2912976613],"iteration":527,"passed_time":0.6738620052,"remaining_time":0.6023917926},
{"learn":[0.2910834672],"iteration":528,"passed_time":0.6751081282,"remaining_time":0.6010887115},
{"learn":[0.290880603],"iteration":529,"passed_time":0.67637009,"remaining_time":0.5997998911},
{"learn":[0.2907168908],"iteration":530,"passed_time":0.6776300445,"remaining_time":0.598509399},
{"learn":[0.2905923763],"iteration":531,"passed_time":0.6788806315,"remaining_time":0.5972107811},
{"learn":[0.2904897907],"iteration":532,"passed_time":0.6801194343,"remaining_time":0.5959020184},
{"learn":[0.2903063654],"iteration":533,"passed_time":0.6814182078,"remaining_time":0.5946458518},
{"learn":[0.290054504],"iteration":534,"passed_time":0.682760571,"remaining_time":0.5934274122},
{"learn":[0.2899746923],"iteration":535,"passed_time":0.6840079623,"remaining_time":0.5921262957},
{"learn":[0.2896638973],"iteration":536,"passed_time":0.6852742483,"remaining_time":0.5908416703},
{"learn":[0.2895342204],"iteration":537,"passed_time":0.6864984207,"remaining_time":0.5895209486},
{"learn":[0.289391569],"iteration":538,"passed_time":0.6877189978,"remaining_time":0.5881975102},
{"learn":[0.2892097656],"iteration":539,"passed_time":0.6889766054,"remaining_time":0.5869059972},
{"learn":[0.2890362997],"iteration":540,"passed_time":0.6902355666,"remaining_time":0.585615758},
{"learn":[0.2889137953],"iteration":541,"passed_time":0.6914666297,"remaining_time":0.5843020598},
{"learn":[0.2887742734],"iteration":542,"passed_time":0.6927249164,"remaining_time":0.5830115779},
{"learn":[0.2886632131],"iteration":543,"passed_time":0.6939745547,"remaining_time":0.581713965},
{"learn":[0.2884110319],"iteration":544,"passed_time":0.6952188202,"remaining_time":0.5804120425},
{"learn":[0.2882619161],"iteration":545,"passed_time":0.6964740809,"remaining_time":0.5791194739},
{"learn":[0.2881663431],"iteration":546,"passed_time":0.6977217818,"remaining_time":0.5778207809},
{"learn":[0.2879635246],"iteration":547,"passed_time":0.6989790998,"remaining_time":0.5765302064},
{"learn":[0.2877872947],"iteration":548,"passed_time":0.7002230956,"remaining_time":0.575228809},
{"learn":[0.2877112063],"iteration":549,"passed_time":0.7010962575,"remaining_time":0.5736242107},
{"learn":[0.2876601533],"iteration":550,"passed_time":0.7023517626,"remaining_time":0.572333832},
{"learn":[0.2875178217],"iteration":551,"passed_time":0.7036014908,"remaining_time":0.5710388911},
{"learn":[0.2874196675],"iteration":552,"passed_time":0.7048545844,"remaining_time":0.5697468341},
{"learn":[0.2872417701],"iteration":553,"passed_time":0.7060938466,"remaining_time":0.5684437826},
{"learn":[0.2868944271],"iteration":554,"passed_time":0.7073261081,"remaining_time":0.5671353479},
{"learn":[0.286852671],"iteration":555,"passed_time":0.7082019464,"remaining_time":0.5655425616},
{"learn":[0.2865778986],"iteration":556,"passed_time":0.7094527432,"remaining_time":0.5642505659},
{"learn":[0.2864835134],"iteration":557,"passed_time":0.7107118388,"remaining_time":0.5629652917},
{"learn":[0.2863542248],"iteration":558,"passed_time":0.711945089,"remaining_time":0.5616597214},
{"learn":[0.2861804848],"iteration":559,"passed_time":0.7131888951,"remaining_time":0.5603627033},
{"learn":[0.2860156762],"iteration":560,"passed_time":0.7144234735,"remaining_time":0.559058654},
{"learn":[0.2859282579],"iteration":561,"passed_time":0.7156572929,"remaining_time":0.5577542603},
{"learn":[0.2857110029],"iteration":562,"passed_time":0.7169142514,"remaining_time":0.5564680779},
{"learn":[0.2855072478],"iteration":563,"passed_time":0.7181506374,"remaining_time":0.5551660956},
{"learn":[0.2851841178],"iteration":564,"passed_time":0.7193984881,"remaining_time":0.5538731723},
{"learn":[0.2849764795],"iteration":565,"passed_time":0.7206522808,"remaining_time":0.5525849644},
{"learn":[0.2848097293],"iteration":566,"passed_time":0.7216671332,"remaining_time":0.5511144068},
{"learn":[0.2847019584],"iteration":567,"passed_time":0.7229082928,"remaining_time":0.5498175748},
{"learn":[0.2845655201],"iteration":568,"passed_time":0.7241606574,"remaining_time":0.5485294259},
{"learn":[0.2843538844],"iteration":569,"passed_time":0.7254151892,"remaining_time":0.5472430374},
{"learn":[0.2842573977],"iteration":570,"passed_time":0.7266518049,"remaining_time":0.5459433},
{"learn":[0.2839643741],"iteration":571,"passed_time":0.7279319124,"remaining_time":0.544676326},
{"learn":[0.2837512079],"iteration":572,"passed_time":0.7293918593,"remaining_time":0.5435433227},
{"learn":[0.2835506965],"iteration":573,"passed_time":0.730727932,"remaining_time":0.5423172457},
{"learn":[0.2833865731],"iteration":574,"passed_time":0.7320065515,"remaining_time":0.5410483206},
{"learn":[0.2832628353],"iteration":575,"passed_time":0.7332432071,"remaining_time":0.5397484719},
{"learn":[0.2831115723],"iteration":576,"passed_time":0.7345006949,"remaining_time":0.5384641143},
{"learn":[0.2830822882],"iteration":577,"passed_time":0.7357254764,"remaining_time":0.5371559707},
{"learn":[0.2828733022],"iteration":578,"passed_time":0.7370035666,"remaining_time":0.5358868766},
{"learn":[0.2826052454],"iteration":579,"passed_time":0.738255372,"remaining_time":0.5345987177},
{"learn":[0.2825015633],"iteration":580,"passed_time":0.7394832794,"remaining_time":0.5332934493},
{"learn":[0.2822441055],"iteration":581,"passed_time":0.7407487065,"remaining_time":0.532015394},
{"learn":[0.2819946198],"iteration":582,"passed_time":0.7420089806,"remaining_time":0.5307336962},
{"learn":[0.2817998189],"iteration":583,"passed_time":0.7432735935,"remaining_time":0.5294551625},
{"learn":[0.2816366321],"iteration":584,"passed_time":0.7445448528,"remaining_time":0.5281813913},
{"learn":[0.2814495978],"iteration":585,"passed_time":0.7457999738,"remaining_time":0.5268962272},
{"learn":[0.281186041],"iteration":586,"passed_time":0.7470377679,"remaining_time":0.5255989747},
{"learn":[0.280991126],"iteration":587,"passed_time":0.7482910413,"remaining_time":0.5243127704},
{"learn":[0.2807843785],"iteration":588,"passed_time":0.7495464918,"remaining_time":0.5230281972},
{"learn":[0.2806698462],"iteration":589,"passed_time":0.7507832673,"remaining_time":0.5217307451},
{"learn":[0.2803957819],"iteration":590,"passed_time":0.7520412144,"remaining_time":0.5204481501},
{"learn":[0.2802821862],"iteration":591,"passed_time":0.7532899539,"remaining_time":0.5191592926},
{"learn":[0.2801085603],"iteration":592,"passed_time":0.7545390729,"remaining_time":0.5178708308},
{"learn":[0.2799091453],"iteration":593,"passed_time":0.7557837278,"remaining_time":0.5165794503},
{"learn":[0.2797992044],"iteration":594,"passed_time":0.7570574339,"remaining_time":0.5153080012},
{"learn":[0.2796428475],"iteration":595,"passed_time":0.7583409822,"remaining_time":0.5140432161},
{"learn":[0.2795485536],"iteration":596,"passed_time":0.7596057602,"remaining_time":0.5127656974},
{"learn":[0.2793179358],"iteration":597,"passed_time":0.7608754516,"remaining_time":0.5114915243},
{"learn":[0.2792183882],"iteration":598,"passed_time":0.7621204361,"remaining_time":0.5102008262},
{"learn":[0.2789411716],"iteration":599,"passed_time":0.7633604373,"remaining_time":0.5089069582},
{"learn":[0.2788058983],"iteration":600,"passed_time":0.764600808,"remaining_time":0.5076135148},
{"learn":[0.2786641378],"iteration":601,"passed_time":0.7658447938,"remaining_time":0.5063226378},
{"learn":[0.2785213265],"iteration":602,"passed_time":0.7670840959,"remaining_time":0.5050288326},
{"learn":[0.2784595147],"iteration":603,"passed_time":0.7683558946,"remaining_time":0.5037565137},
{"learn":[0.2782112396],"iteration":604,"passed_time":0.7696398769,"remaining_time":0.502492151},
{"learn":[0.2778824218],"iteration":605,"passed_time":0.7709184265,"remaining_time":0.5012241915},
{"learn":[0.2776418218],"iteration":606,"passed_time":0.7721876186,"remaining_time":0.4999501386},
{"learn":[0.2775426168],"iteration":607,"passed_time":0.7734698832,"remaining_time":0.49868453},
{"learn":[0.2773409175],"iteration":608,"passed_time":0.7748150694,"remaining_time":0.4974592646},
{"learn":[0.2771115788],"iteration":609,"passed_time":0.7760936889,"remaining_time":0.496191047},
{"learn":[0.2769881837],"iteration":610,"passed_time":0.7773352979,"remaining_time":0.4948992322},
{"learn":[0.276880093],"iteration":611,"passed_time":0.7786009691,"remaining_time":0.4936228366},
{"learn":[0.2767989336],"iteration":612,"passed_time":0.779834429,"remaining_time":0.4923261403},
{"learn":[0.2767985909],"iteration":613,"passed_time":0.7804786472,"remaining_time":0.4906592147},
{"learn":[0.2766852008],"iteration":614,"passed_time":0.7817307921,"remaining_time":0.4893761869},
{"learn":[0.2766044754],"iteration":615,"passed_time":0.7829878205,"remaining_time":0.4880963037},
{"learn":[0.2761435366],"iteration":616,"passed_time":0.7842563734,"remaining_time":0.4868236483},
{"learn":[0.2759130329],"iteration":617,"passed_time":0.7854919805,"remaining_time":0.4855306417},
{"learn":[0.2757993915],"iteration":618,"passed_time":0.7867183399,"remaining_time":0.4842321284},
{"learn":[0.2757218869],"iteration":619,"passed_time":0.788064289,"remaining_time":0.4830071449},
{"learn":[0.2755470961],"iteration":620,"passed_time":0.7894008713,"remaining_time":0.4817760551},
{"learn":[0.2754028914],"iteration":621,"passed_time":0.7906792012,"remaining_time":0.4805092252},
{"learn":[0.2752025856],"iteration":622,"passed_time":0.7919292589,"remaining_time":0.4792252498},
{"learn":[0.2751230023],"iteration":623,"passed_time":0.7931541703,"remaining_time":0.4779262308},
{"learn":[0.2749120747],"iteration":624,"passed_time":0.7943884191,"remaining_time":0.4766330515},
{"learn":[0.2747254286],"iteration":625,"passed_time":0.7957104972,"remaining_time":0.4753925335},
{"learn":[0.2746252186],"iteration":626,"passed_time":0.7971393757,"remaining_time":0.4742152905},
{"learn":[0.274436905],"iteration":627,"passed_time":0.7983974227,"remaining_time":0.4729360529},
{"learn":[0.2743344107],"iteration":628,"passed_time":0.799628346,"remaining_time":0.4716408845},
{"learn":[0.2741482443],"iteration":629,"passed_time":0.8008999682,"remaining_time":0.4703698226},
{"learn":[0.2738997636],"iteration":630,"passed_time":0.8021399993,"remaining_time":0.4690802849},
{"learn":[0.2738033226],"iteration":631,"passed_time":0.8034652362,"remaining_time":0.4678405173},
{"learn":[0.2736582271],"iteration":632,"passed_time":0.8047233331,"remaining_time":0.4665615533},
{"learn":[0.2732604706],"iteration":633,"passed_time":0.8060306712,"remaining_time":0.4653110815},
{"learn":[0.2730816139],"iteration":634,"passed_time":0.807292613,"remaining_time":0.4640343366},
{"learn":[0.2729878226],"iteration":635,"passed_time":0.8085778966,"remaining_time":0.4627709974},
{"learn":[0.2727730574],"iteration":636,"passed_time":0.809888733,"remaining_time":0.4615221508},
{"learn":[0.2726152614],"iteration":637,"passed_time":0.8111231017,"remaining_time":0.4602297223},
{"learn":[0.272378202],"iteration":638,"passed_time":0.8123716115,"remaining_time":0.4589454644},
{"learn":[0.2722838396],"iteration":639,"passed_time":0.8136245953,"remaining_time":0.4576638349},
{"learn":[0.2719226083],"iteration":640,"passed_time":0.8149536384,"remaining_time":0.4564248926},
{"learn":[0.2719223799],"iteration":641,"passed_time":0.8155896176,"remaining_time":0.4547991948},
{"learn":[0.2717808021],"iteration":642,"passed_time":0.8169765811,"remaining_time":0.4535935295},
{"learn":[0.2715922601],"iteration":643,"passed_time":0.8182483099,"remaining_time":0.4523235999},
{"learn":[0.2715074002],"iteration":644,"passed_time":0.8194739103,"remaining_time":0.4510282762},
{"learn":[0.2713066604],"iteration":645,"passed_time":0.8207327962,"remaining_time":0.4497514084},
{"learn":[0.2711504177],"iteration":646,"passed_time":0.8220917782,"remaining_time":0.4485292082},
{"learn":[0.2710708344],"iteration":647,"passed_time":0.8234681699,"remaining_time":0.4473160429},
{"learn":[0.2709187034],"iteration":648,"passed_time":0.8247169893,"remaining_time":0.4460333794},
{"learn":[0.2706244691],"iteration":649,"passed_time":0.8259759052,"remaining_time":0.4447562566},
{"learn":[0.2703605698],"iteration":650,"passed_time":0.8272660589,"remaining_time":0.4434959363},
{"learn":[0.2702992376],"iteration":651,"passed_time":0.8285714529,"remaining_time":0.4422436589},
{"learn":[0.2700155567],"iteration":652,"passed_time":0.8299526419,"remaining_time":0.4410314958},
{"learn":[0.2697773551],"iteration":653,"passed_time":0.8312025598,"remaining_time":0.4397493665},
{"learn":[0.2694658519],"iteration":654,"passed_time":0.8324587493,"remaining_time":0.4384706389},
{"learn":[0.2693560937],"iteration":655,"passed_time":0.8338091861,"remaining_time":0.4372414024},
{"learn":[0.2692942134],"iteration":656,"passed_time":0.8350867167,"remaining_time":0.4359737349},
{"learn":[0.2692279473],"iteration":657,"passed_time":0.8364414847,"remaining_time":0.434746182},
{"learn":[0.2690337861],"iteration":658,"passed_time":0.8377133732,"remaining_time":0.433475357},
{"learn":[0.2688907007],"iteration":659,"passed_time":0.8389821359,"remaining_time":0.4322029185},
{"learn":[0.2687997875],"iteration":660,"passed_time":0.8402456023,"remaining_time":0.4309277749},
{"learn":[0.2686995089],"iteration":661,"passed_time":0.8415107998,"remaining_time":0.4296535503},
{"learn":[0.2685463728],"iteration":662,"passed_time":0.8427710239,"remaining_time":0.4283768251},
{"learn":[0.2684382593],"iteration":663,"passed_time":0.8440391904,"remaining_time":0.4271041686},
{"learn":[0.2681042334],"iteration":664,"passed_time":0.8453181794,"remaining_time":0.4258369776},
{"learn":[0.2679354045],"iteration":665,"passed_time":0.8465778243,"remaining_time":0.42456005},
{"learn":[0.2677147688],"iteration":666,"passed_time":0.8479723258,"remaining_time":0.4233505015},
{"learn":[0.2674956636],"iteration":667,"passed_time":0.8494254552,"remaining_time":0.4221695376},
{"learn":[0.2673856998],"iteration":668,"passed_time":0.8506792379,"remaining_time":0.4208891297},
{"learn":[0.2671266887],"iteration":669,"passed_time":0.8519200779,"remaining_time":0.4196024264},
{"learn":[0.2669826667],"iteration":670,"passed_time":0.853203301,"remaining_time":0.4183366409},
{"learn":[0.2668383935],"iteration":671,"passed_time":0.8544987083,"remaining_time":0.4170767505},
{"learn":[0.266604966],"iteration":672,"passed_time":0.855793413,"remaining_time":0.4158164131},
{"learn":[0.2664291016],"iteration":673,"passed_time":0.8570537969,"remaining_time":0.4145393736},
{"learn":[0.2662582854],"iteration":674,"passed_time":0.8583136615,"remaining_time":0.4132621333},
{"learn":[0.2660194443],"iteration":675,"passed_time":0.8595605135,"remaining_time":0.4119787076},
{"learn":[0.2658382119],"iteration":676,"passed_time":0.8608065965,"remaining_time":0.4106950232},
{"learn":[0.2657585372],"iteration":677,"passed_time":0.8621053321,"remaining_time":0.4094364557},
{"learn":[0.2656162285],"iteration":678,"passed_time":0.8633958657,"remaining_time":0.4081738923},
{"learn":[0.2654184124],"iteration":679,"passed_time":0.8646398715,"remaining_time":0.4068893513},
{"learn":[0.265296936],"iteration":680,"passed_time":0.8658747295,"remaining_time":0.4056006442},
{"learn":[0.2652730428],"iteration":681,"passed_time":0.8668908306,"remaining_time":0.404210094},
{"learn":[0.2652085584],"iteration":682,"passed_time":0.8681438044,"remaining_time":0.4029305798},
{"learn":[0.2650839983],"iteration":683,"passed_time":0.8694903697,"remaining_time":0.4016943813},
{"learn":[0.2648954563],"iteration":684,"passed_time":0.8707461397,"remaining_time":0.4004161081},
{"learn":[0.2647901524],"iteration":685,"passed_time":0.871974137,"remaining_time":0.3991251881},
{"learn":[0.264540758],"iteration":686,"passed_time":0.873229192,"remaining_time":0.3978467789},
{"learn":[0.264368023],"iteration":687,"passed_time":0.874537591,"remaining_time":0.3965926285},
{"learn":[0.2642523714],"iteration":688,"passed_time":0.8758592679,"remaining_time":0.395344314},
{"learn":[0.2641072302],"iteration":689,"passed_time":0.8771354607,"remaining_time":0.3940753519},
{"learn":[0.2638771834],"iteration":690,"passed_time":0.8784494345,"remaining_time":0.3928232638},
{"learn":[0.2636970474],"iteration":691,"passed_time":0.8797395587,"remaining_time":0.3915603816},
{"learn":[0.263580505],"iteration":692,"passed_time":0.8810154521,"remaining_time":0.3902911166},
{"learn":[0.2635438885],"iteration":693,"passed_time":0.8823046805,"remaining_time":0.3890277121},
{"learn":[0.2633264507],"iteration":694,"passed_time":0.8835876841,"remaining_time":0.3877615017},
{"learn":[0.2631269444],"iteration":695,"passed_time":0.8848484974,"remaining_time":0.3864855506},
{"learn":[0.2630038918],"iteration":696,"passed_time":0.8861033587,"remaining_time":0.3852070555},
{"learn":[0.2628190275],"iteration":697,"passed_time":0.8873652107,"remaining_time":0.3839316527},
{"learn":[0.2626303484],"iteration":698,"passed_time":0.8887037666,"remaining_time":0.3826893187},
{"learn":[0.2624797707],"iteration":699,"passed_time":0.8899934913,"remaining_time":0.381425782},
{"learn":[0.262264206],"iteration":700,"passed_time":0.8912590583,"remaining_time":0.3801518665},
{"learn":[0.2622082191],"iteration":701,"passed_time":0.8924926081,"remaining_time":0.3788643835},
{"learn":[0.2620556769],"iteration":702,"passed_time":0.8937345167,"remaining_time":0.3775805853},
{"learn":[0.2620016315],"iteration":703,"passed_time":0.8949689753,"remaining_time":0.3762937737},
{"learn":[0.261786775],"iteration":704,"passed_time":0.8963726375,"remaining_time":0.3750779121},
{"learn":[0.2615648144],"iteration":705,"passed_time":0.8976204282,"remaining_time":0.3737966089},
{"learn":[0.2614237163],"iteration":706,"passed_time":0.8990308684,"remaining_time":0.3725828069},
{"learn":[0.2612981968],"iteration":707,"passed_time":0.9002903335,"remaining_time":0.3713061828},
{"learn":[0.2612128572],"iteration":708,"passed_time":0.9016971645,"remaining_time":0.3700900915},
{"learn":[0.2610247492],"iteration":709,"passed_time":0.9029584472,"remaining_time":0.3688140137},
{"learn":[0.2609974981],"iteration":710,"passed_time":0.9037443958,"remaining_time":0.3673447685},
{"learn":[0.2606964568],"iteration":711,"passed_time":0.9050525954,"remaining_time":0.3660886903},
{"learn":[0.2605501963],"iteration":712,"passed_time":0.9062972603,"remaining_time":0.3648068916},
{"learn":[0.2603072435],"iteration":713,"passed_time":0.9076076277,"remaining_time":0.3635515147},
{"learn":[0.260141247],"iteration":714,"passed_time":0.9089429314,"remaining_time":0.3623059237},
{"learn":[0.2599208626],"iteration":715,"passed_time":0.9101808553,"remaining_time":0.3610214566},
{"learn":[0.2598598275],"iteration":716,"passed_time":0.9114255103,"remaining_time":0.359739776},
{"learn":[0.2597149375],"iteration":717,"passed_time":0.9126900886,"remaining_time":0.3584660236},
{"learn":[0.2595698648],"iteration":718,"passed_time":0.9139582321,"remaining_time":0.3571936902},
{"learn":[0.2594352311],"iteration":719,"passed_time":0.9151919417,"remaining_time":0.3559079773},
{"learn":[0.2592823234],"iteration":720,"passed_time":0.9164490899,"remaining_time":0.3546314786},
{"learn":[0.2590581243],"iteration":721,"passed_time":0.9177195104,"remaining_time":0.3533601439},
{"learn":[0.2588273922],"iteration":722,"passed_time":0.9189757199,"remaining_time":0.3520833671},
{"learn":[0.2586317919],"iteration":723,"passed_time":0.9202244893,"remaining_time":0.3508038108},
{"learn":[0.2585386859],"iteration":724,"passed_time":0.9215016564,"remaining_time":0.3495351111},
{"learn":[0.2583249943],"iteration":725,"passed_time":0.9227546402,"remaining_time":0.3482572609},
{"learn":[0.2580070267],"iteration":726,"passed_time":0.9240257897,"remaining_time":0.3469863007},
{"learn":[0.2579633975],"iteration":727,"passed_time":0.9250402626,"remaining_time":0.3456194388},
{"learn":[0.2578850706],"iteration":728,"passed_time":0.9262930367,"remaining_time":0.3443421302},
{"learn":[0.2576565314],"iteration":729,"passed_time":0.9275685903,"remaining_time":0.3430733142},
{"learn":[0.2575837095],"iteration":730,"passed_time":0.9288301326,"remaining_time":0.3417993238},
{"learn":[0.2574130075],"iteration":731,"passed_time":0.9300806198,"remaining_time":0.3405213198},
{"learn":[0.257322437],"iteration":732,"passed_time":0.9313263733,"remaining_time":0.3392416667},
{"learn":[0.2572262016],"iteration":733,"passed_time":0.9325690309,"remaining_time":0.3379609839},
{"learn":[0.2570215556],"iteration":734,"passed_time":0.9338180999,"remaining_time":0.3366827163},
{"learn":[0.2567492045],"iteration":735,"passed_time":0.9351376703,"remaining_time":0.3354298165},
{"learn":[0.2565145435],"iteration":736,"passed_time":0.9363934703,"remaining_time":0.3341539792},
{"learn":[0.2562736922],"iteration":737,"passed_time":0.9376498995,"remaining_time":0.3328784196},
{"learn":[0.256083734],"iteration":738,"passed_time":0.9390696003,"remaining_time":0.331660576},
{"learn":[0.255863578],"iteration":739,"passed_time":0.9403073744,"remaining_time":0.3303782667},
{"learn":[0.2556074451],"iteration":740,"passed_time":0.9415746292,"remaining_time":0.3291063819},
{"learn":[0.2554888011],"iteration":741,"passed_time":0.9428373799,"remaining_time":0.3278329434},
{"learn":[0.2553728755],"iteration":742,"passed_time":0.9440912825,"remaining_time":0.3265564732},
{"learn":[0.2552641452],"iteration":743,"passed_time":0.9453111606,"remaining_time":0.3252683563},
{"learn":[0.2551315673],"iteration":744,"passed_time":0.9465634852,"remaining_time":0.3239915285},
{"learn":[0.2550555703],"iteration":745,"passed_time":0.9478006003,"remaining_time":0.3227095878},
{"learn":[0.2548762339],"iteration":746,"passed_time":0.9490599555,"remaining_time":0.3214352995},
{"learn":[0.2547713868],"iteration":747,"passed_time":0.9502902996,"remaining_time":0.3201512774},
{"learn":[0.2546528342],"iteration":748,"passed_time":0.9515267955,"remaining_time":0.3188694602},
{"learn":[0.2545086524],"iteration":749,"passed_time":0.9527540038,"remaining_time":0.3175846679},
{"learn":[0.2544075515],"iteration":750,"passed_time":0.9541111975,"remaining_time":0.3163431267},
{"learn":[0.2542883593],"iteration":751,"passed_time":0.955458587,"remaining_time":0.3150980447},
{"learn":[0.2541729819],"iteration":752,"passed_time":0.9567209283,"remaining_time":0.3138247932},
{"learn":[0.2540462745],"iteration":753,"passed_time":0.9579784061,"remaining_time":0.3125499839},
{"learn":[0.2539203667],"iteration":754,"passed_time":0.9593249947,"remaining_time":0.3113041373},
{"learn":[0.2538113623],"iteration":755,"passed_time":0.9606995988,"remaining_time":0.3100670663},
{"learn":[0.2536435613],"iteration":756,"passed_time":0.9620274671,"remaining_time":0.3088146295},
{"learn":[0.253406182],"iteration":757,"passed_time":0.9633010533,"remaining_time":0.3075446635},
{"learn":[0.2532138939],"iteration":758,"passed_time":0.9645594199,"remaining_time":0.3062698553},
{"learn":[0.2530716765],"iteration":759,"passed_time":0.9658119443,"remaining_time":0.3049932456},
{"learn":[0.2529004491],"iteration":760,"passed_time":0.9670454142,"remaining_time":0.3037107148},
{"learn":[0.25270526],"iteration":761,"passed_time":0.9682732317,"remaining_time":0.3024265474},
{"learn":[0.2525685933],"iteration":762,"passed_time":0.9695117848,"remaining_time":0.3011458624},
{"learn":[0.2524491727],"iteration":763,"passed_time":0.9707460137,"remaining_time":0.2998639519},
{"learn":[0.252180819],"iteration":764,"passed_time":0.9720369068,"remaining_time":0.2985995727},
{"learn":[0.2520224291],"iteration":765,"passed_time":0.9733116614,"remaining_time":0.2973301942},
{"learn":[0.2518514302],"iteration":766,"passed_time":0.9746806401,"remaining_time":0.2960894252},
{"learn":[0.2516998931],"iteration":767,"passed_time":0.9759083277,"remaining_time":0.2948056407},
{"learn":[0.2515339652],"iteration":768,"passed_time":0.9771696903,"remaining_time":0.2935321176},
{"learn":[0.251400702],"iteration":769,"passed_time":0.9784281867,"remaining_time":0.2922577701},
{"learn":[0.2512886824],"iteration":770,"passed_time":0.9796625554,"remaining_time":0.2909762973},
{"learn":[0.2511382417],"iteration":771,"passed_time":0.9809129827,"remaining_time":0.2896996892},
{"learn":[0.2509636793],"iteration":772,"passed_time":0.9822897415,"remaining_time":0.2884602475},
{"learn":[0.2508383197],"iteration":773,"passed_time":0.9836092563,"remaining_time":0.2872037363},
{"learn":[0.2507323305],"iteration":774,"passed_time":0.9849217905,"remaining_time":0.2859450359},
{"learn":[0.2505828035],"iteration":775,"passed_time":0.9861707397,"remaining_time":0.2846678424},
{"learn":[0.2502945997],"iteration":776,"passed_time":0.9875046456,"remaining_time":0.2834151042},
{"learn":[0.2500626341],"iteration":777,"passed_time":0.9888545098,"remaining_time":0.282166711},
{"learn":[0.2499925077],"iteration":778,"passed_time":0.9900978864,"remaining_time":0.2808878471},
{"learn":[0.2497261413],"iteration":779,"passed_time":0.9913642224,"remaining_time":0.2796155499},
{"learn":[0.2496185303],"iteration":780,"passed_time":0.9926227694,"remaining_time":0.2783410839},
{"learn":[0.2494682266],"iteration":781,"passed_time":0.9938961659,"remaining_time":0.2770707982},
{"learn":[0.249367674],"iteration":782,"passed_time":0.9952510024,"remaining_time":0.2758230747},
{"learn":[0.2490693966],"iteration":783,"passed_time":0.9965242694,"remaining_time":0.2745526048},
{"learn":[0.2488736592],"iteration":784,"passed_time":0.9978263572,"remaining_time":0.2732900214},
{"learn":[0.2487180105],"iteration":785,"passed_time":0.9990978862,"remaining_time":0.2720190174},
{"learn":[0.2485688718],"iteration":786,"passed_time":1.000449795,"remaining_time":0.2707697665},
{"learn":[0.2482793203],"iteration":787,"passed_time":1.00178616,"remaining_time":0.2695160736},
{"learn":[0.2481954883],"iteration":788,"passed_time":1.003030036,"remaining_time":0.2682374368},
{"learn":[0.2480379436],"iteration":789,"passed_time":1.004267511,"remaining_time":0.2669571864},
{"learn":[0.24773375],"iteration":790,"passed_time":1.005540614,"remaining_time":0.2656864581},
{"learn":[0.2475873753],"iteration":791,"passed_time":1.006801131,"remaining_time":0.2644124183},
{"learn":[0.2473818842],"iteration":792,"passed_time":1.008069135,"remaining_time":0.2631403668},
{"learn":[0.2472964532],"iteration":793,"passed_time":1.009299349,"remaining_time":0.2618585213},
{"learn":[0.2472233116],"iteration":794,"passed_time":1.010577275,"remaining_time":0.2605891086},
{"learn":[0.247040366],"iteration":795,"passed_time":1.011826534,"remaining_time":0.2593123277},
{"learn":[0.2469508234],"iteration":796,"passed_time":1.01314877,"remaining_time":0.2580542036},
{"learn":[0.2467718753],"iteration":797,"passed_time":1.014467532,"remaining_time":0.2567950395},
{"learn":[0.2465881759],"iteration":798,"passed_time":1.015760203,"remaining_time":0.2555291624},
{"learn":[0.2463098857],"iteration":799,"passed_time":1.01701807,"remaining_time":0.2542545175},
{"learn":[0.2461902367],"iteration":800,"passed_time":1.018250571,"remaining_time":0.2529736126},
{"learn":[0.246079679],"iteration":801,"passed_time":1.019480127,"remaining_time":0.2516921011},
{"learn":[0.2459318424],"iteration":802,"passed_time":1.020731473,"remaining_time":0.2504160649},
{"learn":[0.2457221939],"iteration":803,"passed_time":1.022137572,"remaining_time":0.249177816},
{"learn":[0.2455780578],"iteration":804,"passed_time":1.023411118,"remaining_time":0.247907041},
{"learn":[0.2453521911],"iteration":805,"passed_time":1.024657091,"remaining_time":0.2466296225},
{"learn":[0.2452991052],"iteration":806,"passed_time":1.025898501,"remaining_time":0.2453511903},
{"learn":[0.2451617761],"iteration":807,"passed_time":1.027245502,"remaining_time":0.244097941},
{"learn":[0.2450974516],"iteration":808,"passed_time":1.028735548,"remaining_time":0.242878232},
{"learn":[0.2449851579],"iteration":809,"passed_time":1.029996901,"remaining_time":0.2416042112},
{"learn":[0.2448482856],"iteration":810,"passed_time":1.031257195,"remaining_time":0.2403299751},
{"learn":[0.24468985],"iteration":811,"passed_time":1.032541037,"remaining_time":0.2390612253},
{"learn":[0.2444828285],"iteration":812,"passed_time":1.033822623,"remaining_time":0.2377919194},
{"learn":[0.2443907047],"iteration":813,"passed_time":1.035219811,"remaining_time":0.2365489985},
{"learn":[0.2442437589],"iteration":814,"passed_time":1.036486666,"remaining_time":0.2352761143},
{"learn":[0.2440161334],"iteration":815,"passed_time":1.03772468,"remaining_time":0.2339967415},
{"learn":[0.2439013041],"iteration":816,"passed_time":1.03899097,"remaining_time":0.2327238035},
{"learn":[0.2437617136],"iteration":817,"passed_time":1.040285883,"remaining_time":0.2314572503},
{"learn":[0.2436479808],"iteration":818,"passed_time":1.041903422,"remaining_time":0.2302619285},
{"learn":[0.2433433761],"iteration":819,"passed_time":1.043367585,"remaining_time":0.2290319088},
{"learn":[0.2431043294],"iteration":820,"passed_time":1.044674996,"remaining_time":0.2277671428},
{"learn":[0.2429391553],"iteration":821,"passed_time":1.046067443,"remaining_time":0.2265206871},
{"learn":[0.2428524223],"iteration":822,"passed_time":1.047374449,"remaining_time":0.2252555013},
{"learn":[0.2427619888],"iteration":823,"passed_time":1.04865205,"remaining_time":0.2239839331},
{"learn":[0.2425758225],"iteration":824,"passed_time":1.049895177,"remaining_time":0.2227050376},
{"learn":[0.2424431532],"iteration":825,"passed_time":1.05115653,"remaining_time":0.221430068},
{"learn":[0.2423046592],"iteration":826,"passed_time":1.052418671,"remaining_time":0.2201552965},
{"learn":[0.2421308963],"iteration":827,"passed_time":1.053691419,"remaining_time":0.2188827585},
{"learn":[0.2418834892],"iteration":828,"passed_time":1.055137749,"remaining_time":0.2176460254},
{"learn":[0.241734716],"iteration":829,"passed_time":1.056401728,"remaining_time":0.2163714383},
{"learn":[0.2415902143],"iteration":830,"passed_time":1.057650158,"remaining_time":0.2150937144},
{"learn":[0.2413805202],"iteration":831,"passed_time":1.0589458,"remaining_time":0.2138255942},
{"learn":[0.2411540825],"iteration":832,"passed_time":1.060214433,"remaining_time":0.2125519931},
{"learn":[0.2410188321],"iteration":833,"passed_time":1.061576236,"remaining_time":0.2112969486},
{"learn":[0.2407607119],"iteration":834,"passed_time":1.062857652,"remaining_time":0.2100257635},
{"learn":[0.2406334791],"iteration":835,"passed_time":1.064109117,"remaining_time":0.2087486785},
{"learn":[0.2404766197],"iteration":836,"passed_time":1.065336176,"remaining_time":0.2074669016},
{"learn":[0.2401783195],"iteration":837,"passed_time":1.066755674,"remaining_time":0.2062224573},
{"learn":[0.2400532797],"iteration":838,"passed_time":1.068045878,"remaining_time":0.2049527846},
{"learn":[0.2399316205],"iteration":839,"passed_time":1.069283672,"remaining_time":0.2036730803},
{"learn":[0.2398080426],"iteration":840,"passed_time":1.070569222,"remaining_time":0.2024025045},
{"learn":[0.2396168737],"iteration":841,"passed_time":1.071827259,"remaining_time":0.2011267303},
{"learn":[0.2395051054],"iteration":842,"passed_time":1.07312963,"remaining_time":0.1998592549},
{"learn":[0.2394272353],"iteration":843,"passed_time":1.074447242,"remaining_time":0.198594514},
{"learn":[0.2393720022],"iteration":844,"passed_time":1.075702194,"remaining_time":0.1973181539},
{"learn":[0.239217998],"iteration":845,"passed_time":1.076946219,"remaining_time":0.1960398555},
{"learn":[0.2390976181],"iteration":846,"passed_time":1.078181377,"remaining_time":0.1947600362},
{"learn":[0.2389820579],"iteration":847,"passed_time":1.079478533,"remaining_time":0.1934914352},
{"learn":[0.2388151934],"iteration":848,"passed_time":1.080816044,"remaining_time":0.1922299442},
{"learn":[0.2387111001],"iteration":849,"passed_time":1.082083029,"remaining_time":0.1909558287},
{"learn":[0.2385075735],"iteration":850,"passed_time":1.083354868,"remaining_time":0.1896825797},
{"learn":[0.2383249705],"iteration":851,"passed_time":1.084595768,"remaining_time":0.1884039597},
{"learn":[0.2382101413],"iteration":852,"passed_time":1.085829697,"remaining_time":0.1871242268},
{"learn":[0.2380221247],"iteration":853,"passed_time":1.087147418,"remaining_time":0.1858589262},
{"learn":[0.2378857093],"iteration":854,"passed_time":1.088432638,"remaining_time":0.1845879913},
{"learn":[0.2377351772],"iteration":855,"passed_time":1.089686631,"remaining_time":0.1833117696},
{"learn":[0.2376568275],"iteration":856,"passed_time":1.090908876,"remaining_time":0.1820303025},
{"learn":[0.2375633788],"iteration":857,"passed_time":1.092205176,"remaining_time":0.1807612297},
{"learn":[0.2374528896],"iteration":858,"passed_time":1.093476376,"remaining_time":0.1794879732},
{"learn":[0.2373750196],"iteration":859,"passed_time":1.094850627,"remaining_time":0.1782314975},
{"learn":[0.2372758146],"iteration":860,"passed_time":1.096098848,"remaining_time":0.1769544017},
{"learn":[0.237009768],"iteration":861,"passed_time":1.097363336,"remaining_time":0.1756799772},
{"learn":[0.2368032033],"iteration":862,"passed_time":1.098605574,"remaining_time":0.1744020436},
{"learn":[0.2367467823],"iteration":863,"passed_time":1.099857529,"remaining_time":0.1731257222},
{"learn":[0.2366630417],"iteration":864,"passed_time":1.101269997,"remaining_time":0.1718745081},
{"learn":[0.236541611],"iteration":865,"passed_time":1.102540038,"remaining_time":0.1706008834},
{"learn":[0.2362594148],"iteration":866,"passed_time":1.103797375,"remaining_time":0.1693253183},
{"learn":[0.2360408121],"iteration":867,"passed_time":1.105037626,"remaining_time":0.1680471966},
{"learn":[0.2359625993],"iteration":868,"passed_time":1.106301555,"remaining_time":0.1667727316},
{"learn":[0.2356573322],"iteration":869,"passed_time":1.107580355,"remaining_time":0.1655005128},
{"learn":[0.2354455365],"iteration":870,"passed_time":1.108807773,"remaining_time":0.164220669},
{"learn":[0.235349895],"iteration":871,"passed_time":1.110047624,"remaining_time":0.1629427706},
{"learn":[0.2352467154],"iteration":872,"passed_time":1.111301537,"remaining_time":0.1616670048},
{"learn":[0.235145546],"iteration":873,"passed_time":1.112636949,"remaining_time":0.1604030383},
{"learn":[0.234997184],"iteration":874,"passed_time":1.113978585,"remaining_time":0.1591397979},
{"learn":[0.2348671188],"iteration":875,"passed_time":1.115236253,"remaining_time":0.1578644924},
{"learn":[0.234764556],"iteration":876,"passed_time":1.116455861,"remaining_time":0.1565838893},
{"learn":[0.2346418689],"iteration":877,"passed_time":1.117694205,"remaining_time":0.1553060285},
{"learn":[0.2344335682],"iteration":878,"passed_time":1.119100783,"remaining_time":0.1540514162},
{"learn":[0.234314376],"iteration":879,"passed_time":1.120432085,"remaining_time":0.1527861935},
{"learn":[0.234226204],"iteration":880,"passed_time":1.121695415,"remaining_time":0.1515116395},
{"learn":[0.2341129965],"iteration":881,"passed_time":1.122960523,"remaining_time":0.1502373489},
{"learn":[0.2339985556],"iteration":882,"passed_time":1.124206686,"remaining_time":0.1489605688},
{"learn":[0.2339367438],"iteration":883,"passed_time":1.125449054,"remaining_time":0.14768336},
{"learn":[0.2338424957],"iteration":884,"passed_time":1.126726891,"remaining_time":0.146410839},
{"learn":[0.2335955911],"iteration":885,"passed_time":1.128069136,"remaining_time":0.1451465931},
{"learn":[0.2333021792],"iteration":886,"passed_time":1.129350152,"remaining_time":0.1438743711},
{"learn":[0.2332663622],"iteration":887,"passed_time":1.130604854,"remaining_time":0.1425988104},
{"learn":[0.2330769522],"iteration":888,"passed_time":1.131838294,"remaining_time":0.1413206418},
{"learn":[0.2329414505],"iteration":889,"passed_time":1.133074889,"remaining_time":0.1400429639},
{"learn":[0.2328891868],"iteration":890,"passed_time":1.134516254,"remaining_time":0.1387904284},
{"learn":[0.2327171143],"iteration":891,"passed_time":1.135780253,"remaining_time":0.1375159948},
{"learn":[0.2326302443],"iteration":892,"passed_time":1.137047558,"remaining_time":0.1362419806},
{"learn":[0.2324622605],"iteration":893,"passed_time":1.138312925,"remaining_time":0.1349677517},
{"learn":[0.232308165],"iteration":894,"passed_time":1.139624138,"remaining_time":0.1336989212},
{"learn":[0.2321189149],"iteration":895,"passed_time":1.141015934,"remaining_time":0.1324393495},
{"learn":[0.2320494509],"iteration":896,"passed_time":1.142260998,"remaining_time":0.1311626342},
{"learn":[0.2318960635],"iteration":897,"passed_time":1.143506203,"remaining_time":0.1298860052},
{"learn":[0.2318218711],"iteration":898,"passed_time":1.144747362,"remaining_time":0.1286089918},
{"learn":[0.2316414839],"iteration":899,"passed_time":1.146041253,"remaining_time":0.127337917},
{"learn":[0.2313570491],"iteration":900,"passed_time":1.147394736,"remaining_time":0.1260733394},
{"learn":[0.2313174174],"iteration":901,"passed_time":1.148756351,"remaining_time":0.1248094484},
{"learn":[0.2312517452],"iteration":902,"passed_time":1.150061145,"remaining_time":0.1235392371},
{"learn":[0.2310621981],"iteration":903,"passed_time":1.151322268,"remaining_time":0.1222643117},
{"learn":[0.2307865348],"iteration":904,"passed_time":1.152604124,"remaining_time":0.1209915931},
{"learn":[0.230708779],"iteration":905,"passed_time":1.153963858,"remaining_time":0.1197269345},
{"learn":[0.2305965309],"iteration":906,"passed_time":1.155209751,"remaining_time":0.1184503934},
{"learn":[0.2304906331],"iteration":907,"passed_time":1.156485814,"remaining_time":0.1171769768},
{"learn":[0.2303343676],"iteration":908,"passed_time":1.15772987,"remaining_time":0.11590035},
{"learn":[0.2302076146],"iteration":909,"passed_time":1.159024475,"remaining_time":0.1146287942},
{"learn":[0.2300959604],"iteration":910,"passed_time":1.160308148,"remaining_time":0.1133561198},
{"learn":[0.2297973861],"iteration":911,"passed_time":1.161587516,"remaining_time":0.1120830059},
{"learn":[0.2296934984],"iteration":912,"passed_time":1.162879606,"remaining_time":0.1108110906},
{"learn":[0.2295950244],"iteration":913,"passed_time":1.164182273,"remaining_time":0.1095401263},
{"learn":[0.2293003562],"iteration":914,"passed_time":1.165460643,"remaining_time":0.1082668357},
{"learn":[0.2291838138],"iteration":915,"passed_time":1.166761554,"remaining_time":0.106995601},
{"learn":[0.2290293528],"iteration":916,"passed_time":1.168030377,"remaining_time":0.1057213972},
{"learn":[0.2289085388],"iteration":917,"passed_time":1.169336573,"remaining_time":0.1044505435},
{"learn":[0.2287983923],"iteration":918,"passed_time":1.17057942,"remaining_time":0.1031740294},
{"learn":[0.2287430906],"iteration":919,"passed_time":1.171803473,"remaining_time":0.1018959541},
{"learn":[0.2284417524],"iteration":920,"passed_time":1.173087042,"remaining_time":0.1006231014},
{"learn":[0.2283648874],"iteration":921,"passed_time":1.174355745,"remaining_time":0.0993489676},
{"learn":[0.2282730377],"iteration":922,"passed_time":1.175587577,"remaining_time":0.09807176972},
{"learn":[0.2280166763],"iteration":923,"passed_time":1.176817442,"remaining_time":0.09679450822},
{"learn":[0.2278555225],"iteration":924,"passed_time":1.178083758,"remaining_time":0.09552030471},
{"learn":[0.2277676245],"iteration":925,"passed_time":1.179418672,"remaining_time":0.09425160013},
{"learn":[0.2276668206],"iteration":926,"passed_time":1.180865465,"remaining_time":0.09299156303},
{"learn":[0.2275510777],"iteration":927,"passed_time":1.182115592,"remaining_time":0.09171586493},
{"learn":[0.2275436538],"iteration":928,"passed_time":1.182992,"remaining_time":0.09041165985},
{"learn":[0.2274201216],"iteration":929,"passed_time":1.184245853,"remaining_time":0.0891367846},
{"learn":[0.2272465415],"iteration":930,"passed_time":1.185608252,"remaining_time":0.08786999935},
{"learn":[0.2270671136],"iteration":931,"passed_time":1.186944238,"remaining_time":0.08660108173},
{"learn":[0.2268846249],"iteration":932,"passed_time":1.188219831,"remaining_time":0.08532768349},
{"learn":[0.2267164356],"iteration":933,"passed_time":1.189467642,"remaining_time":0.08405231732},
{"learn":[0.2265937485],"iteration":934,"passed_time":1.190711348,"remaining_time":0.08277672475},
{"learn":[0.2263676306],"iteration":935,"passed_time":1.191985104,"remaining_time":0.08150325499},
{"learn":[0.2262839814],"iteration":936,"passed_time":1.193281187,"remaining_time":0.08023128582},
{"learn":[0.226206888],"iteration":937,"passed_time":1.194534661,"remaining_time":0.07895644878},
{"learn":[0.226048224],"iteration":938,"passed_time":1.195800637,"remaining_time":0.0776824695},
{"learn":[0.2259327323],"iteration":939,"passed_time":1.197065075,"remaining_time":0.07640840907},
{"learn":[0.2258687048],"iteration":940,"passed_time":1.198359512,"remaining_time":0.07513624995},
{"learn":[0.2257364239],"iteration":941,"passed_time":1.199668413,"remaining_time":0.0738649341},
{"learn":[0.2256312799],"iteration":942,"passed_time":1.200932262,"remaining_time":0.0725908154},
{"learn":[0.2254629763],"iteration":943,"passed_time":1.202184207,"remaining_time":0.07131601228},
{"learn":[0.2254201466],"iteration":944,"passed_time":1.203419494,"remaining_time":0.07004028804},
{"learn":[0.2253368629],"iteration":945,"passed_time":1.204669033,"remaining_time":0.06876546276},
{"learn":[0.2251282195],"iteration":946,"passed_time":1.205989606,"remaining_time":0.06749466645},
{"learn":[0.2250054182],"iteration":947,"passed_time":1.207382852,"remaining_time":0.0662277514},
{"learn":[0.2248399929],"iteration":948,"passed_time":1.208649758,"remaining_time":0.06495378044},
{"learn":[0.2247634248],"iteration":949,"passed_time":1.209897518,"remaining_time":0.06367881676},
{"learn":[0.2247153185],"iteration":950,"passed_time":1.21112211,"remaining_time":0.06240271651},
{"learn":[0.2245698118],"iteration":951,"passed_time":1.212447066,"remaining_time":0.06113178482},
{"learn":[0.2243513918],"iteration":952,"passed_time":1.213880433,"remaining_time":0.05986608642},
{"learn":[0.2241875426],"iteration":953,"passed_time":1.215140108,"remaining_time":0.05859166139},
{"learn":[0.223979356],"iteration":954,"passed_time":1.216414353,"remaining_time":0.05731795382},
{"learn":[0.2239444299],"iteration":955,"passed_time":1.217649591,"remaining_time":0.05604244979},
{"learn":[0.2236986674],"iteration":956,"passed_time":1.218930118,"remaining_time":0.05476906486},
{"learn":[0.2234955748],"iteration":957,"passed_time":1.220304924,"remaining_time":0.05349979832},
{"learn":[0.2234328036],"iteration":958,"passed_time":1.221565677,"remaining_time":0.05222543562},
{"learn":[0.2232193176],"iteration":959,"passed_time":1.222826321,"remaining_time":0.05095109669},
{"learn":[0.223008824],"iteration":960,"passed_time":1.22406001,"remaining_time":0.0496756924},
{"learn":[0.2228840582],"iteration":961,"passed_time":1.225344028,"remaining_time":0.04840236283},
{"learn":[0.222615065],"iteration":962,"passed_time":1.226650105,"remaining_time":0.04712985867},
{"learn":[0.2224731902],"iteration":963,"passed_time":1.227912217,"remaining_time":0.04585564296},
{"learn":[0.2223677492],"iteration":964,"passed_time":1.229143929,"remaining_time":0.04458034976},
{"learn":[0.2222995644],"iteration":965,"passed_time":1.230368351,"remaining_time":0.04330489021},
{"learn":[0.2220281727],"iteration":966,"passed_time":1.23167436,"remaining_time":0.04203232045},
{"learn":[0.2218326866],"iteration":967,"passed_time":1.233015335,"remaining_time":0.04076083751},
{"learn":[0.2218056182],"iteration":968,"passed_time":1.234247297,"remaining_time":0.03948572363},
{"learn":[0.2217459764],"iteration":969,"passed_time":1.235561669,"remaining_time":0.03821324749},
{"learn":[0.2214798156],"iteration":970,"passed_time":1.236968527,"remaining_time":0.03694344725},
{"learn":[0.2211723556],"iteration":971,"passed_time":1.238306424,"remaining_time":0.03567137847},
{"learn":[0.2209588011],"iteration":972,"passed_time":1.239662134,"remaining_time":0.03439966868},
{"learn":[0.2208636392],"iteration":973,"passed_time":1.240934592,"remaining_time":0.03312556406},
{"learn":[0.2207396502],"iteration":974,"passed_time":1.242187796,"remaining_time":0.03185096912},
{"learn":[0.2205493493],"iteration":975,"passed_time":1.243457627,"remaining_time":0.03057682689},
{"learn":[0.2204736036],"iteration":976,"passed_time":1.244744701,"remaining_time":0.02930309941},
{"learn":[0.220410741],"iteration":977,"passed_time":1.24607922,"remaining_time":0.0280304119},
{"learn":[0.220228298],"iteration":978,"passed_time":1.247380089,"remaining_time":0.02675687628},
{"learn":[0.2200063146],"iteration":979,"passed_time":1.24862079,"remaining_time":0.02548205693},
{"learn":[0.2198745819],"iteration":980,"passed_time":1.249885897,"remaining_time":0.02420777987},
{"learn":[0.2196739562],"iteration":981,"passed_time":1.251274728,"remaining_time":0.02293578932},
{"learn":[0.2196281113],"iteration":982,"passed_time":1.252664,"remaining_time":0.02166356867},
{"learn":[0.2195432743],"iteration":983,"passed_time":1.253980176,"remaining_time":0.02038992156},
{"learn":[0.219469356],"iteration":984,"passed_time":1.255254661,"remaining_time":0.01911555322},
{"learn":[0.2192009794],"iteration":985,"passed_time":1.256552378,"remaining_time":0.0178415145},
{"learn":[0.218953481],"iteration":986,"passed_time":1.257884586,"remaining_time":0.01656788209},
{"learn":[0.2188919433],"iteration":987,"passed_time":1.259180053,"remaining_time":0.01529368485},
{"learn":[0.2187458884],"iteration":988,"passed_time":1.260440976,"remaining_time":0.0140190604},
{"learn":[0.2185953563],"iteration":989,"passed_time":1.261679659,"remaining_time":0.01274423898},
{"learn":[0.2182761552],"iteration":990,"passed_time":1.262945346,"remaining_time":0.01146973573},
{"learn":[0.2182234804],"iteration":991,"passed_time":1.264218852,"remaining_time":0.01019531332},
{"learn":[0.2180923873],"iteration":992,"passed_time":1.265592644,"remaining_time":0.008921599708},
{"learn":[0.2177753791],"iteration":993,"passed_time":1.267086406,"remaining_time":0.007648408892},
{"learn":[0.2176544738],"iteration":994,"passed_time":1.268347909,"remaining_time":0.006373607582},
{"learn":[0.2173649451],"iteration":995,"passed_time":1.269624741,"remaining_time":0.005098894541},
{"learn":[0.2172529483],"iteration":996,"passed_time":1.270880611,"remaining_time":0.003824114176},
{"learn":[0.2170856042],"iteration":997,"passed_time":1.27231246,"remaining_time":0.002549724369},
{"learn":[0.2169638993],"iteration":998,"passed_time":1.27359823,"remaining_time":0.001274873103},
{"learn":[0.2167850654],"iteration":999,"passed_time":1.274885728,"remaining_time":0}
]}